# Comparing `tmp/fediverse_pasture-0.2.8.tar.gz` & `tmp/fediverse_pasture-0.2.9.tar.gz`

## filetype from file(1)

```diff
@@ -1 +1 @@
-gzip compressed data, was "fediverse_pasture-0.2.8.tar", max compression
+gzip compressed data, was "fediverse_pasture-0.2.9.tar", max compression
```

## Comparing `fediverse_pasture-0.2.8.tar` & `fediverse_pasture-0.2.9.tar`

### file list

```diff
@@ -1,80 +1,84 @@
--rw-r--r--   0        0        0     1062 2024-03-11 18:31:16.444405 fediverse_pasture-0.2.8/LICENSE
--rw-r--r--   0        0        0     1567 2024-03-11 18:31:16.444405 fediverse_pasture-0.2.8/README.md
--rw-r--r--   0        0        0        0 2024-03-11 18:31:16.548406 fediverse_pasture-0.2.8/fediverse_pasture/__init__.py
--rw-r--r--   0        0        0     2876 2024-03-11 18:31:16.448405 fediverse_pasture-0.2.8/fediverse_pasture/data_provider/__init__.py
--rw-r--r--   0        0        0     5193 2024-03-11 18:32:32.357231 fediverse_pasture-0.2.8/fediverse_pasture/data_provider/__pycache__/__init__.cpython-311.pyc
--rw-r--r--   0        0        0     1781 2024-03-11 18:32:33.869247 fediverse_pasture-0.2.8/fediverse_pasture/data_provider/__pycache__/generate.cpython-311.pyc
--rw-r--r--   0        0        0     1359 2024-03-11 18:32:33.869247 fediverse_pasture-0.2.8/fediverse_pasture/data_provider/__pycache__/models.cpython-311.pyc
--rw-r--r--   0        0        0     4188 2024-03-11 18:32:33.873247 fediverse_pasture-0.2.8/fediverse_pasture/data_provider/__pycache__/test_data_provider.cpython-311-pytest-8.1.1.pyc
--rw-r--r--   0        0        0     2930 2024-03-11 18:32:33.877247 fediverse_pasture-0.2.8/fediverse_pasture/data_provider/__pycache__/test_generate.cpython-311-pytest-8.1.1.pyc
--rw-r--r--   0        0        0     1537 2024-03-11 18:31:16.448405 fediverse_pasture-0.2.8/fediverse_pasture/data_provider/generate.py
--rw-r--r--   0        0        0     1024 2024-03-11 18:31:16.448405 fediverse_pasture-0.2.8/fediverse_pasture/data_provider/models.py
--rw-r--r--   0        0        0      603 2024-03-11 18:31:16.448405 fediverse_pasture-0.2.8/fediverse_pasture/data_provider/test_data_provider.py
--rw-r--r--   0        0        0      320 2024-03-11 18:31:16.448405 fediverse_pasture-0.2.8/fediverse_pasture/data_provider/test_generate.py
--rw-r--r--   0        0        0      621 2024-03-11 18:31:16.448405 fediverse_pasture-0.2.8/fediverse_pasture/http_signature.py
--rw-r--r--   0        0        0     2706 2024-03-11 18:31:16.448405 fediverse_pasture-0.2.8/fediverse_pasture/one_actor.py
--rw-r--r--   0        0        0     4656 2024-03-11 18:31:16.448405 fediverse_pasture-0.2.8/fediverse_pasture/runner/__init__.py
--rw-r--r--   0        0        0     7471 2024-03-11 18:32:33.881247 fediverse_pasture-0.2.8/fediverse_pasture/runner/__pycache__/__init__.cpython-311.pyc
--rw-r--r--   0        0        0     5833 2024-03-11 18:32:33.921248 fediverse_pasture-0.2.8/fediverse_pasture/runner/__pycache__/entry.cpython-311.pyc
--rw-r--r--   0        0        0     1120 2024-03-11 18:32:34.117250 fediverse_pasture-0.2.8/fediverse_pasture/runner/__pycache__/models.cpython-311.pyc
--rw-r--r--   0        0        0     7374 2024-03-11 18:32:33.929248 fediverse_pasture-0.2.8/fediverse_pasture/runner/__pycache__/result_store.cpython-311.pyc
--rw-r--r--   0        0        0    11191 2024-03-11 18:32:33.913247 fediverse_pasture-0.2.8/fediverse_pasture/runner/__pycache__/test_activity_sender.cpython-311-pytest-8.1.1.pyc
--rw-r--r--   0        0        0     9002 2024-03-11 18:32:33.921248 fediverse_pasture-0.2.8/fediverse_pasture/runner/__pycache__/test_entry.cpython-311-pytest-8.1.1.pyc
--rw-r--r--   0        0        0     9377 2024-03-11 18:32:33.925248 fediverse_pasture-0.2.8/fediverse_pasture/runner/__pycache__/test_result_store.cpython-311-pytest-8.1.1.pyc
--rw-r--r--   0        0        0     3133 2024-03-11 18:32:34.125250 fediverse_pasture-0.2.8/fediverse_pasture/runner/__pycache__/test_verify_actor.cpython-311-pytest-8.1.1.pyc
--rw-r--r--   0        0        0     5278 2024-03-11 18:32:34.125250 fediverse_pasture-0.2.8/fediverse_pasture/runner/__pycache__/verify_actor.cpython-311.pyc
--rw-r--r--   0        0        0     4874 2024-03-11 18:31:16.448405 fediverse_pasture-0.2.8/fediverse_pasture/runner/application/__init__.py
--rw-r--r--   0        0        0     7260 2024-03-11 18:32:33.885247 fediverse_pasture-0.2.8/fediverse_pasture/runner/application/__pycache__/__init__.cpython-311.pyc
--rw-r--r--   0        0        0     2725 2024-03-11 18:32:33.885247 fediverse_pasture-0.2.8/fediverse_pasture/runner/application/__pycache__/bovine.cpython-311.pyc
--rw-r--r--   0        0        0     5235 2024-03-11 18:32:33.885247 fediverse_pasture-0.2.8/fediverse_pasture/runner/application/__pycache__/firefish.cpython-311.pyc
--rw-r--r--   0        0        0     3452 2024-03-11 18:32:33.885247 fediverse_pasture-0.2.8/fediverse_pasture/runner/application/__pycache__/mastodon.cpython-311.pyc
--rw-r--r--   0        0        0     4116 2024-03-11 18:32:33.889247 fediverse_pasture-0.2.8/fediverse_pasture/runner/application/__pycache__/test_application.cpython-311-pytest-8.1.1.pyc
--rw-r--r--   0        0        0     1434 2024-03-11 18:31:16.448405 fediverse_pasture-0.2.8/fediverse_pasture/runner/application/bovine.py
--rw-r--r--   0        0        0     2887 2024-03-11 18:31:16.448405 fediverse_pasture-0.2.8/fediverse_pasture/runner/application/firefish.py
--rw-r--r--   0        0        0     1810 2024-03-11 18:31:16.448405 fediverse_pasture-0.2.8/fediverse_pasture/runner/application/mastodon.py
--rw-r--r--   0        0        0      749 2024-03-11 18:31:16.448405 fediverse_pasture-0.2.8/fediverse_pasture/runner/application/test_application.py
--rw-r--r--   0        0        0     3096 2024-03-11 18:31:16.448405 fediverse_pasture-0.2.8/fediverse_pasture/runner/entry.py
--rw-r--r--   0        0        0      410 2024-03-11 18:31:16.448405 fediverse_pasture-0.2.8/fediverse_pasture/runner/models.py
--rw-r--r--   0        0        0     4129 2024-03-11 18:31:16.448405 fediverse_pasture-0.2.8/fediverse_pasture/runner/result_store.py
--rw-r--r--   0        0        0     1808 2024-03-11 18:31:16.448405 fediverse_pasture-0.2.8/fediverse_pasture/runner/test_activity_sender.py
--rw-r--r--   0        0        0     1134 2024-03-11 18:31:16.448405 fediverse_pasture-0.2.8/fediverse_pasture/runner/test_entry.py
--rw-r--r--   0        0        0     1652 2024-03-11 18:31:16.448405 fediverse_pasture-0.2.8/fediverse_pasture/runner/test_result_store.py
--rw-r--r--   0        0        0     1592 2024-03-11 18:31:16.448405 fediverse_pasture-0.2.8/fediverse_pasture/runner/test_verify_actor.py
--rw-r--r--   0        0        0     2712 2024-03-11 18:31:16.448405 fediverse_pasture-0.2.8/fediverse_pasture/runner/verify_actor.py
--rw-r--r--   0        0        0     6266 2024-03-11 18:31:16.448405 fediverse_pasture-0.2.8/fediverse_pasture/server/__init__.py
--rw-r--r--   0        0        0    10512 2024-03-11 18:32:34.129250 fediverse_pasture-0.2.8/fediverse_pasture/server/__pycache__/__init__.cpython-311.pyc
--rw-r--r--   0        0        0     3001 2024-03-11 18:32:36.061271 fediverse_pasture-0.2.8/fediverse_pasture/server/__pycache__/http_signature.cpython-311.pyc
--rw-r--r--   0        0        0     2099 2024-03-11 18:32:36.065271 fediverse_pasture-0.2.8/fediverse_pasture/server/__pycache__/image_provider_blueprint.cpython-311.pyc
--rw-r--r--   0        0        0     1193 2024-03-11 18:32:36.161272 fediverse_pasture-0.2.8/fediverse_pasture/server/__pycache__/parser.cpython-311.pyc
--rw-r--r--   0        0        0     7624 2024-03-11 18:32:36.033271 fediverse_pasture-0.2.8/fediverse_pasture/server/__pycache__/test_actor_public_key.cpython-311-pytest-8.1.1.pyc
--rw-r--r--   0        0        0     6127 2024-03-11 18:32:36.041271 fediverse_pasture-0.2.8/fediverse_pasture/server/__pycache__/test_assets_blueprint.cpython-311-pytest-8.1.1.pyc
--rw-r--r--   0        0        0     6353 2024-03-11 18:32:36.049271 fediverse_pasture-0.2.8/fediverse_pasture/server/__pycache__/test_blueprint.cpython-311-pytest-8.1.1.pyc
--rw-r--r--   0        0        0     3497 2024-03-11 18:32:36.057271 fediverse_pasture-0.2.8/fediverse_pasture/server/__pycache__/test_blueprint_http_check.cpython-311-pytest-8.1.1.pyc
--rw-r--r--   0        0        0     3917 2024-03-11 18:32:36.061271 fediverse_pasture-0.2.8/fediverse_pasture/server/__pycache__/test_http_signature.cpython-311-pytest-8.1.1.pyc
--rw-r--r--   0        0        0     2125 2024-03-11 18:32:36.065271 fediverse_pasture-0.2.8/fediverse_pasture/server/__pycache__/test_image_provider_blueprint.cpython-311-pytest-8.1.1.pyc
--rw-r--r--   0        0        0     3621 2024-03-11 18:32:36.161272 fediverse_pasture-0.2.8/fediverse_pasture/server/__pycache__/test_parser.cpython-311-pytest-8.1.1.pyc
--rw-r--r--   0        0        0     6224 2024-03-11 18:32:36.165272 fediverse_pasture-0.2.8/fediverse_pasture/server/__pycache__/test_verify_actor.cpython-311-pytest-8.1.1.pyc
--rw-r--r--   0        0        0    10939 2024-03-11 18:32:36.025271 fediverse_pasture-0.2.8/fediverse_pasture/server/__pycache__/utils.cpython-311.pyc
--rw-r--r--   0        0        0    16897 2024-03-11 18:32:36.169272 fediverse_pasture-0.2.8/fediverse_pasture/server/__pycache__/verify_actor.cpython-311.pyc
--rw-r--r--   0        0        0     2203 2024-03-11 18:31:16.448405 fediverse_pasture-0.2.8/fediverse_pasture/server/http_signature.py
--rw-r--r--   0        0        0     1245 2024-03-11 18:31:16.448405 fediverse_pasture-0.2.8/fediverse_pasture/server/image_provider_blueprint.py
--rw-r--r--   0        0        0      346 2024-03-11 18:31:16.448405 fediverse_pasture-0.2.8/fediverse_pasture/server/parser.py
--rw-r--r--   0        0        0     3328 2024-03-11 18:31:16.448405 fediverse_pasture-0.2.8/fediverse_pasture/server/test_actor_public_key.py
--rw-r--r--   0        0        0      879 2024-03-11 18:31:16.448405 fediverse_pasture-0.2.8/fediverse_pasture/server/test_assets_blueprint.py
--rw-r--r--   0        0        0     1167 2024-03-11 18:31:16.448405 fediverse_pasture-0.2.8/fediverse_pasture/server/test_blueprint.py
--rw-r--r--   0        0        0      877 2024-03-11 18:31:16.448405 fediverse_pasture-0.2.8/fediverse_pasture/server/test_blueprint_http_check.py
--rw-r--r--   0        0        0      830 2024-03-11 18:31:16.448405 fediverse_pasture-0.2.8/fediverse_pasture/server/test_http_signature.py
--rw-r--r--   0        0        0      482 2024-03-11 18:31:16.448405 fediverse_pasture-0.2.8/fediverse_pasture/server/test_image_provider_blueprint.py
--rw-r--r--   0        0        0      626 2024-03-11 18:31:16.448405 fediverse_pasture-0.2.8/fediverse_pasture/server/test_parser.py
--rw-r--r--   0        0        0     1385 2024-03-11 18:31:16.448405 fediverse_pasture-0.2.8/fediverse_pasture/server/test_verify_actor.py
--rw-r--r--   0        0        0     6930 2024-03-11 18:31:16.448405 fediverse_pasture-0.2.8/fediverse_pasture/server/utils.py
--rw-r--r--   0        0        0    10051 2024-03-11 18:31:16.448405 fediverse_pasture-0.2.8/fediverse_pasture/server/verify_actor.py
--rw-r--r--   0        0        0    19735 2024-03-11 18:31:16.448405 fediverse_pasture-0.2.8/fediverse_pasture/templates/FediverseLogo.svg
--rw-r--r--   0        0        0       72 2024-03-11 18:31:16.448405 fediverse_pasture-0.2.8/fediverse_pasture/templates/FediverseLogo.svg.license
--rw-r--r--   0        0        0     3013 2024-03-11 18:31:16.448405 fediverse_pasture-0.2.8/fediverse_pasture/templates/index.html.j2
--rw-r--r--   0        0        0     1786 2024-03-11 18:31:16.448405 fediverse_pasture-0.2.8/fediverse_pasture/templates/styles.css
--rw-r--r--   0        0        0     7154 2024-03-11 18:31:16.448405 fediverse_pasture-0.2.8/fediverse_pasture/templates/verify_actor_result.html.j2
--rw-r--r--   0        0        0     1812 2024-03-11 18:31:16.448405 fediverse_pasture-0.2.8/fediverse_pasture/types.py
--rw-r--r--   0        0        0     5457 2024-03-11 18:31:16.448405 fediverse_pasture-0.2.8/fediverse_pasture/verify_actor.py
--rw-r--r--   0        0        0     1167 2024-03-11 18:31:16.448405 fediverse_pasture-0.2.8/pyproject.toml
--rw-r--r--   0        0        0     2553 1970-01-01 00:00:00.000000 fediverse_pasture-0.2.8/PKG-INFO
+-rw-r--r--   0        0        0     1062 2024-03-31 10:02:14.320128 fediverse_pasture-0.2.9/LICENSE
+-rw-r--r--   0        0        0     1567 2024-03-31 10:02:14.320128 fediverse_pasture-0.2.9/README.md
+-rw-r--r--   0        0        0        0 2024-03-31 10:02:14.424129 fediverse_pasture-0.2.9/fediverse_pasture/__init__.py
+-rw-r--r--   0        0        0     2876 2024-03-31 10:02:14.320128 fediverse_pasture-0.2.9/fediverse_pasture/data_provider/__init__.py
+-rw-r--r--   0        0        0     5193 2024-03-31 10:03:06.424730 fediverse_pasture-0.2.9/fediverse_pasture/data_provider/__pycache__/__init__.cpython-311.pyc
+-rw-r--r--   0        0        0     1781 2024-03-31 10:03:07.808745 fediverse_pasture-0.2.9/fediverse_pasture/data_provider/__pycache__/generate.cpython-311.pyc
+-rw-r--r--   0        0        0     1359 2024-03-31 10:03:07.808745 fediverse_pasture-0.2.9/fediverse_pasture/data_provider/__pycache__/models.cpython-311.pyc
+-rw-r--r--   0        0        0     4188 2024-03-31 10:03:07.812746 fediverse_pasture-0.2.9/fediverse_pasture/data_provider/__pycache__/test_data_provider.cpython-311-pytest-8.1.1.pyc
+-rw-r--r--   0        0        0     2930 2024-03-31 10:03:07.816746 fediverse_pasture-0.2.9/fediverse_pasture/data_provider/__pycache__/test_generate.cpython-311-pytest-8.1.1.pyc
+-rw-r--r--   0        0        0     1537 2024-03-31 10:02:14.320128 fediverse_pasture-0.2.9/fediverse_pasture/data_provider/generate.py
+-rw-r--r--   0        0        0     1024 2024-03-31 10:02:14.320128 fediverse_pasture-0.2.9/fediverse_pasture/data_provider/models.py
+-rw-r--r--   0        0        0      603 2024-03-31 10:02:14.320128 fediverse_pasture-0.2.9/fediverse_pasture/data_provider/test_data_provider.py
+-rw-r--r--   0        0        0      320 2024-03-31 10:02:14.320128 fediverse_pasture-0.2.9/fediverse_pasture/data_provider/test_generate.py
+-rw-r--r--   0        0        0      621 2024-03-31 10:02:14.320128 fediverse_pasture-0.2.9/fediverse_pasture/http_signature.py
+-rw-r--r--   0        0        0     2706 2024-03-31 10:02:14.320128 fediverse_pasture-0.2.9/fediverse_pasture/one_actor.py
+-rw-r--r--   0        0        0     5484 2024-03-31 10:02:14.320128 fediverse_pasture-0.2.9/fediverse_pasture/runner/__init__.py
+-rw-r--r--   0        0        0     8405 2024-03-31 10:03:07.824746 fediverse_pasture-0.2.9/fediverse_pasture/runner/__pycache__/__init__.cpython-311.pyc
+-rw-r--r--   0        0        0     5833 2024-03-31 10:03:07.884746 fediverse_pasture-0.2.9/fediverse_pasture/runner/__pycache__/entry.cpython-311.pyc
+-rw-r--r--   0        0        0     1120 2024-03-31 10:03:08.200750 fediverse_pasture-0.2.9/fediverse_pasture/runner/__pycache__/models.cpython-311.pyc
+-rw-r--r--   0        0        0     7374 2024-03-31 10:03:07.892747 fediverse_pasture-0.2.9/fediverse_pasture/runner/__pycache__/result_store.cpython-311.pyc
+-rw-r--r--   0        0        0     3296 2024-03-31 10:03:07.864746 fediverse_pasture-0.2.9/fediverse_pasture/runner/__pycache__/test_activity_runner.cpython-311-pytest-8.1.1.pyc
+-rw-r--r--   0        0        0    11191 2024-03-31 10:03:07.876746 fediverse_pasture-0.2.9/fediverse_pasture/runner/__pycache__/test_activity_sender.cpython-311-pytest-8.1.1.pyc
+-rw-r--r--   0        0        0     9002 2024-03-31 10:03:07.884746 fediverse_pasture-0.2.9/fediverse_pasture/runner/__pycache__/test_entry.cpython-311-pytest-8.1.1.pyc
+-rw-r--r--   0        0        0     9377 2024-03-31 10:03:07.892747 fediverse_pasture-0.2.9/fediverse_pasture/runner/__pycache__/test_result_store.cpython-311-pytest-8.1.1.pyc
+-rw-r--r--   0        0        0     3133 2024-03-31 10:03:08.204750 fediverse_pasture-0.2.9/fediverse_pasture/runner/__pycache__/test_verify_actor.cpython-311-pytest-8.1.1.pyc
+-rw-r--r--   0        0        0     5278 2024-03-31 10:03:08.204750 fediverse_pasture-0.2.9/fediverse_pasture/runner/__pycache__/verify_actor.cpython-311.pyc
+-rw-r--r--   0        0        0     3655 2024-03-31 10:02:14.320128 fediverse_pasture-0.2.9/fediverse_pasture/runner/application/__init__.py
+-rw-r--r--   0        0        0     5413 2024-03-31 10:03:07.828746 fediverse_pasture-0.2.9/fediverse_pasture/runner/application/__pycache__/__init__.cpython-311.pyc
+-rw-r--r--   0        0        0     2725 2024-03-31 10:03:07.832746 fediverse_pasture-0.2.9/fediverse_pasture/runner/application/__pycache__/bovine.cpython-311.pyc
+-rw-r--r--   0        0        0     5235 2024-03-31 10:03:07.832746 fediverse_pasture-0.2.9/fediverse_pasture/runner/application/__pycache__/firefish.cpython-311.pyc
+-rw-r--r--   0        0        0     3064 2024-03-31 10:03:07.828746 fediverse_pasture-0.2.9/fediverse_pasture/runner/application/__pycache__/mastodon.cpython-311.pyc
+-rw-r--r--   0        0        0     3964 2024-03-31 10:03:07.828746 fediverse_pasture-0.2.9/fediverse_pasture/runner/application/__pycache__/misskey.cpython-311.pyc
+-rw-r--r--   0        0        0     4116 2024-03-31 10:03:07.836746 fediverse_pasture-0.2.9/fediverse_pasture/runner/application/__pycache__/test_application.cpython-311-pytest-8.1.1.pyc
+-rw-r--r--   0        0        0     1434 2024-03-31 10:02:14.320128 fediverse_pasture-0.2.9/fediverse_pasture/runner/application/bovine.py
+-rw-r--r--   0        0        0     2887 2024-03-31 10:02:14.320128 fediverse_pasture-0.2.9/fediverse_pasture/runner/application/firefish.py
+-rw-r--r--   0        0        0     1584 2024-03-31 10:02:14.320128 fediverse_pasture-0.2.9/fediverse_pasture/runner/application/mastodon.py
+-rw-r--r--   0        0        0     2091 2024-03-31 10:02:14.320128 fediverse_pasture-0.2.9/fediverse_pasture/runner/application/misskey.py
+-rw-r--r--   0        0        0      749 2024-03-31 10:02:14.320128 fediverse_pasture-0.2.9/fediverse_pasture/runner/application/test_application.py
+-rw-r--r--   0        0        0     3096 2024-03-31 10:02:14.320128 fediverse_pasture-0.2.9/fediverse_pasture/runner/entry.py
+-rw-r--r--   0        0        0      410 2024-03-31 10:02:14.320128 fediverse_pasture-0.2.9/fediverse_pasture/runner/models.py
+-rw-r--r--   0        0        0     4129 2024-03-31 10:02:14.320128 fediverse_pasture-0.2.9/fediverse_pasture/runner/result_store.py
+-rw-r--r--   0        0        0      966 2024-03-31 10:02:14.320128 fediverse_pasture-0.2.9/fediverse_pasture/runner/test_activity_runner.py
+-rw-r--r--   0        0        0     1808 2024-03-31 10:02:14.320128 fediverse_pasture-0.2.9/fediverse_pasture/runner/test_activity_sender.py
+-rw-r--r--   0        0        0     1134 2024-03-31 10:02:14.320128 fediverse_pasture-0.2.9/fediverse_pasture/runner/test_entry.py
+-rw-r--r--   0        0        0     1652 2024-03-31 10:02:14.320128 fediverse_pasture-0.2.9/fediverse_pasture/runner/test_result_store.py
+-rw-r--r--   0        0        0     1592 2024-03-31 10:02:14.320128 fediverse_pasture-0.2.9/fediverse_pasture/runner/test_verify_actor.py
+-rw-r--r--   0        0        0     2712 2024-03-31 10:02:14.320128 fediverse_pasture-0.2.9/fediverse_pasture/runner/verify_actor.py
+-rw-r--r--   0        0        0     6266 2024-03-31 10:02:14.320128 fediverse_pasture-0.2.9/fediverse_pasture/server/__init__.py
+-rw-r--r--   0        0        0    10512 2024-03-31 10:03:08.212750 fediverse_pasture-0.2.9/fediverse_pasture/server/__pycache__/__init__.cpython-311.pyc
+-rw-r--r--   0        0        0     3001 2024-03-31 10:03:09.196762 fediverse_pasture-0.2.9/fediverse_pasture/server/__pycache__/http_signature.cpython-311.pyc
+-rw-r--r--   0        0        0     2099 2024-03-31 10:03:09.196762 fediverse_pasture-0.2.9/fediverse_pasture/server/__pycache__/image_provider_blueprint.cpython-311.pyc
+-rw-r--r--   0        0        0     1193 2024-03-31 10:03:09.280763 fediverse_pasture-0.2.9/fediverse_pasture/server/__pycache__/parser.cpython-311.pyc
+-rw-r--r--   0        0        0     7624 2024-03-31 10:03:09.176761 fediverse_pasture-0.2.9/fediverse_pasture/server/__pycache__/test_actor_public_key.cpython-311-pytest-8.1.1.pyc
+-rw-r--r--   0        0        0     6127 2024-03-31 10:03:09.180761 fediverse_pasture-0.2.9/fediverse_pasture/server/__pycache__/test_assets_blueprint.cpython-311-pytest-8.1.1.pyc
+-rw-r--r--   0        0        0     6353 2024-03-31 10:03:09.184761 fediverse_pasture-0.2.9/fediverse_pasture/server/__pycache__/test_blueprint.cpython-311-pytest-8.1.1.pyc
+-rw-r--r--   0        0        0     3497 2024-03-31 10:03:09.188762 fediverse_pasture-0.2.9/fediverse_pasture/server/__pycache__/test_blueprint_http_check.cpython-311-pytest-8.1.1.pyc
+-rw-r--r--   0        0        0     3917 2024-03-31 10:03:09.192762 fediverse_pasture-0.2.9/fediverse_pasture/server/__pycache__/test_http_signature.cpython-311-pytest-8.1.1.pyc
+-rw-r--r--   0        0        0     2125 2024-03-31 10:03:09.196762 fediverse_pasture-0.2.9/fediverse_pasture/server/__pycache__/test_image_provider_blueprint.cpython-311-pytest-8.1.1.pyc
+-rw-r--r--   0        0        0     3621 2024-03-31 10:03:09.276763 fediverse_pasture-0.2.9/fediverse_pasture/server/__pycache__/test_parser.cpython-311-pytest-8.1.1.pyc
+-rw-r--r--   0        0        0     6224 2024-03-31 10:03:09.284763 fediverse_pasture-0.2.9/fediverse_pasture/server/__pycache__/test_verify_actor.cpython-311-pytest-8.1.1.pyc
+-rw-r--r--   0        0        0    10939 2024-03-31 10:03:09.172761 fediverse_pasture-0.2.9/fediverse_pasture/server/__pycache__/utils.cpython-311.pyc
+-rw-r--r--   0        0        0    16897 2024-03-31 10:03:09.288763 fediverse_pasture-0.2.9/fediverse_pasture/server/__pycache__/verify_actor.cpython-311.pyc
+-rw-r--r--   0        0        0     2203 2024-03-31 10:02:14.320128 fediverse_pasture-0.2.9/fediverse_pasture/server/http_signature.py
+-rw-r--r--   0        0        0     1245 2024-03-31 10:02:14.320128 fediverse_pasture-0.2.9/fediverse_pasture/server/image_provider_blueprint.py
+-rw-r--r--   0        0        0      346 2024-03-31 10:02:14.320128 fediverse_pasture-0.2.9/fediverse_pasture/server/parser.py
+-rw-r--r--   0        0        0     3328 2024-03-31 10:02:14.320128 fediverse_pasture-0.2.9/fediverse_pasture/server/test_actor_public_key.py
+-rw-r--r--   0        0        0      879 2024-03-31 10:02:14.320128 fediverse_pasture-0.2.9/fediverse_pasture/server/test_assets_blueprint.py
+-rw-r--r--   0        0        0     1167 2024-03-31 10:02:14.320128 fediverse_pasture-0.2.9/fediverse_pasture/server/test_blueprint.py
+-rw-r--r--   0        0        0      877 2024-03-31 10:02:14.320128 fediverse_pasture-0.2.9/fediverse_pasture/server/test_blueprint_http_check.py
+-rw-r--r--   0        0        0      830 2024-03-31 10:02:14.324128 fediverse_pasture-0.2.9/fediverse_pasture/server/test_http_signature.py
+-rw-r--r--   0        0        0      482 2024-03-31 10:02:14.324128 fediverse_pasture-0.2.9/fediverse_pasture/server/test_image_provider_blueprint.py
+-rw-r--r--   0        0        0      626 2024-03-31 10:02:14.324128 fediverse_pasture-0.2.9/fediverse_pasture/server/test_parser.py
+-rw-r--r--   0        0        0     1385 2024-03-31 10:02:14.324128 fediverse_pasture-0.2.9/fediverse_pasture/server/test_verify_actor.py
+-rw-r--r--   0        0        0     6930 2024-03-31 10:02:14.324128 fediverse_pasture-0.2.9/fediverse_pasture/server/utils.py
+-rw-r--r--   0        0        0    10051 2024-03-31 10:02:14.324128 fediverse_pasture-0.2.9/fediverse_pasture/server/verify_actor.py
+-rw-r--r--   0        0        0    19735 2024-03-31 10:02:14.324128 fediverse_pasture-0.2.9/fediverse_pasture/templates/FediverseLogo.svg
+-rw-r--r--   0        0        0       72 2024-03-31 10:02:14.324128 fediverse_pasture-0.2.9/fediverse_pasture/templates/FediverseLogo.svg.license
+-rw-r--r--   0        0        0     3013 2024-03-31 10:02:14.324128 fediverse_pasture-0.2.9/fediverse_pasture/templates/index.html.j2
+-rw-r--r--   0        0        0     1786 2024-03-31 10:02:14.324128 fediverse_pasture-0.2.9/fediverse_pasture/templates/styles.css
+-rw-r--r--   0        0        0     7154 2024-03-31 10:02:14.324128 fediverse_pasture-0.2.9/fediverse_pasture/templates/verify_actor_result.html.j2
+-rw-r--r--   0        0        0     1812 2024-03-31 10:02:14.324128 fediverse_pasture-0.2.9/fediverse_pasture/types.py
+-rw-r--r--   0        0        0     5457 2024-03-31 10:02:14.324128 fediverse_pasture-0.2.9/fediverse_pasture/verify_actor.py
+-rw-r--r--   0        0        0     1167 2024-03-31 10:02:14.324128 fediverse_pasture-0.2.9/pyproject.toml
+-rw-r--r--   0        0        0     2553 1970-01-01 00:00:00.000000 fediverse_pasture-0.2.9/PKG-INFO
```

### Comparing `fediverse_pasture-0.2.8/LICENSE` & `fediverse_pasture-0.2.9/LICENSE`

 * *Files identical despite different names*

### Comparing `fediverse_pasture-0.2.8/README.md` & `fediverse_pasture-0.2.9/README.md`

 * *Files identical despite different names*

### Comparing `fediverse_pasture-0.2.8/fediverse_pasture/data_provider/__init__.py` & `fediverse_pasture-0.2.9/fediverse_pasture/data_provider/__init__.py`

 * *Files identical despite different names*

### Comparing `fediverse_pasture-0.2.8/fediverse_pasture/data_provider/__pycache__/__init__.cpython-311.pyc` & `fediverse_pasture-0.2.9/fediverse_pasture/data_provider/__pycache__/__init__.cpython-311.pyc`

 * *Files 0% similar despite different names*

#### Python bytecode

```diff
@@ -1,9 +1,9 @@
 magic:    0xa70d0d0a
-moddate:  0xf44def65 (Mon Mar 11 18:31:16 2024 UTC)
+moddate:  0xa6340966 (Sun Mar 31 10:02:14 2024 UTC)
 files sz: 2876
 code
    argcount  : 0
    nlocals   : 0
    stacksize : 8
    flags     : 0
    code
```

### Comparing `fediverse_pasture-0.2.8/fediverse_pasture/data_provider/__pycache__/generate.cpython-311.pyc` & `fediverse_pasture-0.2.9/fediverse_pasture/data_provider/__pycache__/generate.cpython-311.pyc`

 * *Files 2% similar despite different names*

#### Python bytecode

```diff
@@ -1,9 +1,9 @@
 magic:    0xa70d0d0a
-moddate:  0xf44def65 (Mon Mar 11 18:31:16 2024 UTC)
+moddate:  0xa6340966 (Sun Mar 31 10:02:14 2024 UTC)
 files sz: 1537
 code
    argcount  : 0
    nlocals   : 0
    stacksize : 4
    flags     : 0
    code
```

### Comparing `fediverse_pasture-0.2.8/fediverse_pasture/data_provider/__pycache__/models.cpython-311.pyc` & `fediverse_pasture-0.2.9/fediverse_pasture/data_provider/__pycache__/models.cpython-311.pyc`

 * *Files 1% similar despite different names*

#### Python bytecode

```diff
@@ -1,9 +1,9 @@
 magic:    0xa70d0d0a
-moddate:  0xf44def65 (Mon Mar 11 18:31:16 2024 UTC)
+moddate:  0xa6340966 (Sun Mar 31 10:02:14 2024 UTC)
 files sz: 1024
 code
    argcount  : 0
    nlocals   : 0
    stacksize : 5
    flags     : 0
    code
```

### Comparing `fediverse_pasture-0.2.8/fediverse_pasture/data_provider/__pycache__/test_data_provider.cpython-311-pytest-8.1.1.pyc` & `fediverse_pasture-0.2.9/fediverse_pasture/data_provider/__pycache__/test_data_provider.cpython-311-pytest-8.1.1.pyc`

 * *Files 2% similar despite different names*

#### Python bytecode

```diff
@@ -1,9 +1,9 @@
 magic:    0xa70d0d0a
-moddate:  0xf44def65 (Mon Mar 11 18:31:16 2024 UTC)
+moddate:  0xa6340966 (Sun Mar 31 10:02:14 2024 UTC)
 files sz: 603
 code
    argcount  : 0
    nlocals   : 0
    stacksize : 2
    flags     : 0
    code
```

### Comparing `fediverse_pasture-0.2.8/fediverse_pasture/data_provider/__pycache__/test_generate.cpython-311-pytest-8.1.1.pyc` & `fediverse_pasture-0.2.9/fediverse_pasture/data_provider/__pycache__/test_generate.cpython-311-pytest-8.1.1.pyc`

 * *Files 8% similar despite different names*

#### Python bytecode

```diff
@@ -1,9 +1,9 @@
 magic:    0xa70d0d0a
-moddate:  0xf44def65 (Mon Mar 11 18:31:16 2024 UTC)
+moddate:  0xa6340966 (Sun Mar 31 10:02:14 2024 UTC)
 files sz: 320
 code
    argcount  : 0
    nlocals   : 0
    stacksize : 3
    flags     : 0
    code
```

### Comparing `fediverse_pasture-0.2.8/fediverse_pasture/data_provider/generate.py` & `fediverse_pasture-0.2.9/fediverse_pasture/data_provider/generate.py`

 * *Files identical despite different names*

### Comparing `fediverse_pasture-0.2.8/fediverse_pasture/data_provider/models.py` & `fediverse_pasture-0.2.9/fediverse_pasture/data_provider/models.py`

 * *Files identical despite different names*

### Comparing `fediverse_pasture-0.2.8/fediverse_pasture/data_provider/test_data_provider.py` & `fediverse_pasture-0.2.9/fediverse_pasture/data_provider/test_data_provider.py`

 * *Files identical despite different names*

### Comparing `fediverse_pasture-0.2.8/fediverse_pasture/http_signature.py` & `fediverse_pasture-0.2.9/fediverse_pasture/http_signature.py`

 * *Files identical despite different names*

### Comparing `fediverse_pasture-0.2.8/fediverse_pasture/one_actor.py` & `fediverse_pasture-0.2.9/fediverse_pasture/one_actor.py`

 * *Files identical despite different names*

### Comparing `fediverse_pasture-0.2.8/fediverse_pasture/runner/__init__.py` & `fediverse_pasture-0.2.9/fediverse_pasture/runner/__init__.py`

 * *Files 20% similar despite different names*

```diff
@@ -46,14 +46,17 @@
     object_factory: ObjectFactory
     bovine_actor: BovineActor
     make_id: Callable
 
     published: datetime | None = None
     note: dict | None = None
     activity: dict | None = None
+    object_id: str | None = None
+
+    sleep_after_getting_inbox: bool = True
 
     def init_create_note(self, modifier: Callable[[dict], dict]):
         """Sets activity to a Create for a Note. Here the Note is
         constructed from a skeleton by applying `modifier` to it.
         To successfully send the note to most applications, modifier
         should set the Note's content, i.e.
 
@@ -61,17 +64,18 @@
         sender.init_create_note(lambda x: {**x, "content": "text"})
         ```
 
         This method can be used to create objects of other types
         by overriding "type".
         """
         published = now_isoformat()
+        self.object_id = self.make_id()
 
         note = self.object_factory.note(
-            id=self.make_id(),
+            id=self.object_id,
             to={"as:Public"},
             published=published,
         ).build()
         del note["@context"]
         self.note = modifier(note)
         self.published = datetime.fromisoformat(published.removesuffix("Z"))
 
@@ -92,14 +96,20 @@
                 create["@context"],
                 {"Hashtag": "as:Hashtag", "sensitive": "as:sensitive"},
             ]
             self.activity = create
 
             remote_inbox = (await self.bovine_actor.get(remote))["inbox"]
 
+            if self.sleep_after_getting_inbox:
+                #
+                # See https://codeberg.org/helge/funfedidev/issues/138#issuecomment-1640700
+                #
+                await asyncio.sleep(0.1)
+
             return await self.bovine_actor.post(remote_inbox, create)
         except Exception as e:
             logger.warning("Posting to inbox of %s failed with %s", remote, repr(e))
             return None
 
     @staticmethod
     def for_actor(bovine_actor, actor_object):
@@ -127,26 +137,39 @@
 
     :param activity_sender: an activity sender
     :param applications: list of applications to run against"""
 
     activity_sender: ActivitySender
     applications: List[ApplicationAdapterForLastActivity]
 
-    async def run_for_modifier(
-        self, modifier: Callable[[dict], dict], wait_time: float = 2.0
-    ):
-        """modifier has the same format as for ActivitySender"""
+    wait_time: float = 0.5
+    """Time in seconds between trying to fetch the activity from remote servers"""
+
+    tries: int = 20
+    """Number of tries to fetch activity from remote servers"""
+
+    async def fetch_activity(self, application, object_id):
+        for _ in range(self.tries):
+            result = await application.fetch_activity(object_id)
+            if result:
+                return result
+            await asyncio.sleep(self.wait_time)
+
+    async def run_for_modifier(self, modifier: Callable[[dict], dict]):
+        """modifier has the same format as for ActivitySender
+
+        :param modifier: modifies the base object being send"""
         self.activity_sender.init_create_note(modifier)
 
         async with asyncio.TaskGroup() as tg:
             for application in self.applications:
                 tg.create_task(self.activity_sender.send(application.actor_uri))
-        await asyncio.sleep(wait_time)
+        await asyncio.sleep(self.wait_time)
 
         result = {"activity": self.activity_sender.activity}
 
         for application in self.applications:
-            result[application.application_name] = await application.fetch_activity(
-                self.activity_sender.published
+            result[application.application_name] = await self.fetch_activity(
+                application, self.activity_sender.object_id
             )
 
         return result
```

### Comparing `fediverse_pasture-0.2.8/fediverse_pasture/runner/__pycache__/__init__.cpython-311.pyc` & `fediverse_pasture-0.2.9/fediverse_pasture/runner/__pycache__/__init__.cpython-311.pyc`

 * *Files 8% similar despite different names*

#### Python bytecode

```diff
@@ -1,10 +1,10 @@
 magic:    0xa70d0d0a
-moddate:  0xf44def65 (Mon Mar 11 18:31:16 2024 UTC)
-files sz: 4656
+moddate:  0xa6340966 (Sun Mar 31 10:02:14 2024 UTC)
+files sz: 5484
 code
    argcount  : 0
    nlocals   : 0
    stacksize : 5
    flags     : 0
    code
       0x9700640064016c005a00640064016c015a01640064026c026d035a0301
@@ -109,28 +109,28 @@
                174 CALL                     2
    
     26         184 PRECALL                  0
                188 CALL                     0
    
     27         198 STORE_NAME              23 (ActivitySender)
    
-   123         200 LOAD_NAME                3 (dataclass)
+   133         200 LOAD_NAME                3 (dataclass)
    
-   124         202 PUSH_NULL
+   134         202 PUSH_NULL
                204 LOAD_BUILD_CLASS
-               206 LOAD_CONST              12 (<code object ActivityRunner, file "/woodpecker/src/codeberg.org/funfedidev/python_fediverse_pasture/fediverse_pasture/runner/__init__.py", line 123>)
+               206 LOAD_CONST              12 (<code object ActivityRunner, file "/woodpecker/src/codeberg.org/funfedidev/python_fediverse_pasture/fediverse_pasture/runner/__init__.py", line 133>)
                208 MAKE_FUNCTION            0
                210 LOAD_CONST              13 ('ActivityRunner')
                212 PRECALL                  2
                216 CALL                     2
    
-   123         226 PRECALL                  0
+   133         226 PRECALL                  0
                230 CALL                     0
    
-   124         240 STORE_NAME              24 (ActivityRunner)
+   134         240 STORE_NAME              24 (ActivityRunner)
                242 LOAD_CONST               1 (None)
                244 RETURN_VALUE
    consts
       0
       None
       ('dataclass',)
       ('datetime',)
@@ -145,18 +145,19 @@
          nlocals   : 0
          stacksize : 4
          flags     : 0
          code
             0x970065005a0164005a02550064015a036504650564023c000000650665
             0564033c0000006507650564043c0000006508650564053c00000064065a
             09650a64067a070000650564073c00000064065a0b650c64067a07000065
-            0564083c00000064065a0d650c64067a070000650564093c000000640a65
-            08650c6701650c6602190000000000000000006602640b84045a0e640c65
-            0f6602640d84045a106511640e8400a6000000ab0000000000000000005a
-            1264065300
+            0564083c00000064065a0d650c64067a070000650564093c00000064065a
+            0e650f64067a0700006505640a3c000000640b5a1065116505640c3c0000
+            00640d6508650c6701650c6602190000000000000000006602640e84045a
+            12640f650f6602641084045a13651464118400a6000000ab000000000000
+            0000005a1564065300
           26           0 RESUME                   0
                        2 LOAD_NAME                0 (__name__)
                        4 STORE_NAME               1 (__module__)
                        6 LOAD_CONST               0 ('ActivitySender')
                        8 STORE_NAME               2 (__qualname__)
                       10 SETUP_ANNOTATIONS
          
@@ -206,143 +207,168 @@
                      100 LOAD_NAME               12 (dict)
                      102 LOAD_CONST               6 (None)
                      104 BINARY_OP                7 (|)
                      108 LOAD_NAME                5 (__annotations__)
                      110 LOAD_CONST               9 ('activity')
                      112 STORE_SUBSCR
          
-          54         116 LOAD_CONST              10 ('modifier')
-                     118 LOAD_NAME                8 (Callable)
-                     120 LOAD_NAME               12 (dict)
-                     122 BUILD_LIST               1
-                     124 LOAD_NAME               12 (dict)
-                     126 BUILD_TUPLE              2
-                     128 BINARY_SUBSCR
-                     138 BUILD_TUPLE              2
-                     140 LOAD_CONST              11 (<code object init_create_note, file "/woodpecker/src/codeberg.org/funfedidev/python_fediverse_pasture/fediverse_pasture/runner/__init__.py", line 54>)
-                     142 MAKE_FUNCTION            4 (annotations)
-                     144 STORE_NAME              14 (init_create_note)
-         
-          78         146 LOAD_CONST              12 ('remote')
-                     148 LOAD_NAME               15 (str)
-                     150 BUILD_TUPLE              2
-                     152 LOAD_CONST              13 (<code object send, file "/woodpecker/src/codeberg.org/funfedidev/python_fediverse_pasture/fediverse_pasture/runner/__init__.py", line 78>)
-                     154 MAKE_FUNCTION            4 (annotations)
-                     156 STORE_NAME              16 (send)
-         
-         104         158 LOAD_NAME               17 (staticmethod)
-         
-         105         160 LOAD_CONST              14 (<code object for_actor, file "/woodpecker/src/codeberg.org/funfedidev/python_fediverse_pasture/fediverse_pasture/runner/__init__.py", line 104>)
-                     162 MAKE_FUNCTION            0
-         
-         104         164 PRECALL                  0
-                     168 CALL                     0
-         
-         105         178 STORE_NAME              18 (for_actor)
-                     180 LOAD_CONST               6 (None)
-                     182 RETURN_VALUE
+          53         116 LOAD_CONST               6 (None)
+                     118 STORE_NAME              14 (object_id)
+                     120 LOAD_NAME               15 (str)
+                     122 LOAD_CONST               6 (None)
+                     124 BINARY_OP                7 (|)
+                     128 LOAD_NAME                5 (__annotations__)
+                     130 LOAD_CONST              10 ('object_id')
+                     132 STORE_SUBSCR
+         
+          55         136 LOAD_CONST              11 (True)
+                     138 STORE_NAME              16 (sleep_after_getting_inbox)
+                     140 LOAD_NAME               17 (bool)
+                     142 LOAD_NAME                5 (__annotations__)
+                     144 LOAD_CONST              12 ('sleep_after_getting_inbox')
+                     146 STORE_SUBSCR
+         
+          57         150 LOAD_CONST              13 ('modifier')
+                     152 LOAD_NAME                8 (Callable)
+                     154 LOAD_NAME               12 (dict)
+                     156 BUILD_LIST               1
+                     158 LOAD_NAME               12 (dict)
+                     160 BUILD_TUPLE              2
+                     162 BINARY_SUBSCR
+                     172 BUILD_TUPLE              2
+                     174 LOAD_CONST              14 (<code object init_create_note, file "/woodpecker/src/codeberg.org/funfedidev/python_fediverse_pasture/fediverse_pasture/runner/__init__.py", line 57>)
+                     176 MAKE_FUNCTION            4 (annotations)
+                     178 STORE_NAME              18 (init_create_note)
+         
+          82         180 LOAD_CONST              15 ('remote')
+                     182 LOAD_NAME               15 (str)
+                     184 BUILD_TUPLE              2
+                     186 LOAD_CONST              16 (<code object send, file "/woodpecker/src/codeberg.org/funfedidev/python_fediverse_pasture/fediverse_pasture/runner/__init__.py", line 82>)
+                     188 MAKE_FUNCTION            4 (annotations)
+                     190 STORE_NAME              19 (send)
+         
+         114         192 LOAD_NAME               20 (staticmethod)
+         
+         115         194 LOAD_CONST              17 (<code object for_actor, file "/woodpecker/src/codeberg.org/funfedidev/python_fediverse_pasture/fediverse_pasture/runner/__init__.py", line 114>)
+                     196 MAKE_FUNCTION            0
+         
+         114         198 PRECALL                  0
+                     202 CALL                     0
+         
+         115         212 STORE_NAME              21 (for_actor)
+                     214 LOAD_CONST               6 (None)
+                     216 RETURN_VALUE
          consts
             'ActivitySender'
             'The ActivitySender class serves as a way to coordinate the process\n    of sending the same activity to multiple Fediverse applications.\n\n    The basic process is\n\n    * Create an Activity with a published timestamp stored in published\n    * Send this activity to applications using `send`\n    * Retrieve the result from said applications\n\n    The usual way to create an ActivitySender is the `for_actor` method,\n    i.e.\n\n    ```python\n    activity_sender = ActivitySender.for_actor(bovine_actor, actor_object)\n    ```\n    '
             'activity_factory'
             'object_factory'
             'bovine_actor'
             'make_id'
             None
             'published'
             'note'
             'activity'
+            'object_id'
+            True
+            'sleep_after_getting_inbox'
             'modifier'
             code
                argcount  : 2
                nlocals   : 4
                stacksize : 5
                flags     : 3
                code
                   0x9700740100000000000000000000a6000000ab0000000000000000007d
-                  027c006a010000000000000000a002000000000000000000000000000000
-                  00000000007c00a0030000000000000000000000000000000000000000a6
-                  000000ab000000000000000000640168017c02ac02a6030000ab03000000
-                  0000000000a0040000000000000000000000000000000000000000a60000
-                  00ab0000000000000000007d037c0364033d0002007c017c03a6010000ab
-                  0100000000000000007c005f020000000000000000740b00000000000000
-                  0000006a0600000000000000007c02a00700000000000000000000000000
-                  000000000000006404a6010000ab010000000000000000a6010000ab0100
-                  000000000000007c005f08000000000000000064055300
-                54           0 RESUME                   0
+                  027c00a0010000000000000000000000000000000000000000a6000000ab
+                  0000000000000000007c005f0200000000000000007c006a030000000000
+                  000000a00400000000000000000000000000000000000000007c006a0200
+                  00000000000000640168017c02ac02a6030000ab030000000000000000a0
+                  050000000000000000000000000000000000000000a6000000ab00000000
+                  00000000007d037c0364033d0002007c017c03a6010000ab010000000000
+                  0000007c005f040000000000000000740d000000000000000000006a0700
+                  000000000000007c02a00800000000000000000000000000000000000000
+                  006404a6010000ab010000000000000000a6010000ab0100000000000000
+                  007c005f09000000000000000064055300
+                57           0 RESUME                   0
                
-                67           2 LOAD_GLOBAL              1 (NULL + now_isoformat)
+                70           2 LOAD_GLOBAL              1 (NULL + now_isoformat)
                             14 PRECALL                  0
                             18 CALL                     0
                             28 STORE_FAST               2 (published)
                
-                69          30 LOAD_FAST                0 (self)
-                            32 LOAD_ATTR                1 (object_factory)
-                            42 LOAD_METHOD              2 (note)
-               
-                70          64 LOAD_FAST                0 (self)
-                            66 LOAD_METHOD              3 (make_id)
-                            88 PRECALL                  0
-                            92 CALL                     0
-               
-                71         102 LOAD_CONST               1 ('as:Public')
-                           104 BUILD_SET                1
-               
-                72         106 LOAD_FAST                2 (published)
-               
-                69         108 KW_NAMES                 2
-                           110 PRECALL                  3
-                           114 CALL                     3
-               
-                73         124 LOAD_METHOD              4 (build)
-                           146 PRECALL                  0
-                           150 CALL                     0
-               
-                69         160 STORE_FAST               3 (note)
-               
-                74         162 LOAD_FAST                3 (note)
-                           164 LOAD_CONST               3 ('@context')
-                           166 DELETE_SUBSCR
-               
-                75         168 PUSH_NULL
-                           170 LOAD_FAST                1 (modifier)
-                           172 LOAD_FAST                3 (note)
-                           174 PRECALL                  1
-                           178 CALL                     1
-                           188 LOAD_FAST                0 (self)
-                           190 STORE_ATTR               2 (note)
-               
-                76         200 LOAD_GLOBAL             11 (NULL + datetime)
-                           212 LOAD_ATTR                6 (fromisoformat)
-                           222 LOAD_FAST                2 (published)
-                           224 LOAD_METHOD              7 (removesuffix)
-                           246 LOAD_CONST               4 ('Z')
-                           248 PRECALL                  1
-                           252 CALL                     1
-                           262 PRECALL                  1
-                           266 CALL                     1
-                           276 LOAD_FAST                0 (self)
-                           278 STORE_ATTR               8 (published)
-                           288 LOAD_CONST               5 (None)
-                           290 RETURN_VALUE
+                71          30 LOAD_FAST                0 (self)
+                            32 LOAD_METHOD              1 (make_id)
+                            54 PRECALL                  0
+                            58 CALL                     0
+                            68 LOAD_FAST                0 (self)
+                            70 STORE_ATTR               2 (object_id)
+               
+                73          80 LOAD_FAST                0 (self)
+                            82 LOAD_ATTR                3 (object_factory)
+                            92 LOAD_METHOD              4 (note)
+               
+                74         114 LOAD_FAST                0 (self)
+                           116 LOAD_ATTR                2 (object_id)
+               
+                75         126 LOAD_CONST               1 ('as:Public')
+                           128 BUILD_SET                1
+               
+                76         130 LOAD_FAST                2 (published)
+               
+                73         132 KW_NAMES                 2
+                           134 PRECALL                  3
+                           138 CALL                     3
+               
+                77         148 LOAD_METHOD              5 (build)
+                           170 PRECALL                  0
+                           174 CALL                     0
+               
+                73         184 STORE_FAST               3 (note)
+               
+                78         186 LOAD_FAST                3 (note)
+                           188 LOAD_CONST               3 ('@context')
+                           190 DELETE_SUBSCR
+               
+                79         192 PUSH_NULL
+                           194 LOAD_FAST                1 (modifier)
+                           196 LOAD_FAST                3 (note)
+                           198 PRECALL                  1
+                           202 CALL                     1
+                           212 LOAD_FAST                0 (self)
+                           214 STORE_ATTR               4 (note)
+               
+                80         224 LOAD_GLOBAL             13 (NULL + datetime)
+                           236 LOAD_ATTR                7 (fromisoformat)
+                           246 LOAD_FAST                2 (published)
+                           248 LOAD_METHOD              8 (removesuffix)
+                           270 LOAD_CONST               4 ('Z')
+                           272 PRECALL                  1
+                           276 CALL                     1
+                           286 PRECALL                  1
+                           290 CALL                     1
+                           300 LOAD_FAST                0 (self)
+                           302 STORE_ATTR               9 (published)
+                           312 LOAD_CONST               5 (None)
+                           314 RETURN_VALUE
                consts
                   'Sets activity to a Create for a Note. Here the Note is\n        constructed from a skeleton by applying `modifier` to it.\n        To successfully send the note to most applications, modifier\n        should set the Note\'s content, i.e.\n\n        ```python\n        sender.init_create_note(lambda x: {**x, "content": "text"})\n        ```\n\n        This method can be used to create objects of other types\n        by overriding "type".\n        '
                   'as:Public'
                   ('id', 'to', 'published')
                   '@context'
                   'Z'
                   None
-               names      ('now_isoformat', 'object_factory', 'note', 'make_id', 'build', 'datetime', 'fromisoformat', 'removesuffix', 'published')
+               names      ('now_isoformat', 'make_id', 'object_id', 'object_factory', 'note', 'build', 'datetime', 'fromisoformat', 'removesuffix', 'published')
                varnames   ('self', 'modifier', 'published', 'note')
                freevars   ()
                cellvars   ()
                filename   '/woodpecker/src/codeberg.org/funfedidev/python_fediverse_pasture/fediverse_pasture/runner/__init__.py'
                name       'init_create_note'
-               firstlineno 54
-               lnotab 0x020d1c0222012601040102fd100424fc020506012001
+               firstlineno 57
+               lnotab 0x020d1c01320222010c01040102fd100424fc020506012001
             'remote'
             code
                argcount  : 2
                nlocals   : 6
                stacksize : 8
                flags     : 131
                code
@@ -352,46 +378,48 @@
                   007c027c00a0030000000000000000000000000000000000000000a60000
                   00ab000000000000000000ac02a6020000ab020000000000000000a00400
                   00000000000000000000000000000000000000a6000000ab000000000000
                   0000007d037c036403190000000000000000006404640564069c0267027c
                   0364033c0000007c037c005f0500000000000000007c006a060000000000
                   000000a00700000000000000000000000000000000000000007c01a60100
                   00ab010000000000000000830064077b0356009703860464081900000000
-                  00000000007d047c006a060000000000000000a008000000000000000000
-                  00000000000000000000007c047c03a6020000ab02000000000000000083
-                  0064077b0356009703860453002300741200000000000000000000240072
-                  347d05741400000000000000000000a00b00000000000000000000000000
-                  0000000000000064097c017419000000000000000000007c05a6010000ab
-                  010000000000000000a6030000ab0300000000000000000100590064077d
-                  057e056407530064077d057e0577017700780359007701
-                78           0 RETURN_GENERATOR
+                  00000000007d047c006a080000000000000000721a741300000000000000
+                  0000006a0a00000000000000006409a6010000ab01000000000000000083
+                  0064077b0356009703860401007c006a060000000000000000a00b000000
+                  00000000000000000000000000000000007c047c03a6020000ab02000000
+                  0000000000830064077b0356009703860453002300741800000000000000
+                  000000240072347d05741a00000000000000000000a00e00000000000000
+                  00000000000000000000000000640a7c01741f000000000000000000007c
+                  05a6010000ab010000000000000000a6030000ab03000000000000000001
+                  00590064077d057e056407530064077d057e0577017700780359007701
+                82           0 RETURN_GENERATOR
                              2 POP_TOP
                              4 RESUME                   0
                
-                83           6 NOP
+                87           6 NOP
                
-                84           8 BUILD_MAP                0
+                88           8 BUILD_MAP                0
                
-                85          10 LOAD_FAST                0 (self)
+                89          10 LOAD_FAST                0 (self)
                             12 LOAD_ATTR                0 (note)
                
-                84          22 DICT_UPDATE              1
+                88          22 DICT_UPDATE              1
                             24 STORE_FAST               2 (note)
                
-                87          26 LOAD_FAST                2 (note)
+                91          26 LOAD_FAST                2 (note)
                             28 LOAD_CONST               1 ('to')
                             30 BINARY_SUBSCR
                             40 LOAD_FAST                1 (remote)
                             42 BUILD_LIST               1
                             44 BINARY_OP                0 (+)
                             48 LOAD_FAST                2 (note)
                             50 LOAD_CONST               1 ('to')
                             52 STORE_SUBSCR
                
-                89          56 LOAD_FAST                0 (self)
+                93          56 LOAD_FAST                0 (self)
                             58 LOAD_ATTR                1 (activity_factory)
                             68 LOAD_METHOD              2 (create)
                             90 LOAD_FAST                2 (note)
                             92 LOAD_FAST                0 (self)
                             94 LOAD_METHOD              3 (make_id)
                            116 PRECALL                  0
                            120 CALL                     0
@@ -399,33 +427,33 @@
                            132 PRECALL                  2
                            136 CALL                     2
                            146 LOAD_METHOD              4 (build)
                            168 PRECALL                  0
                            172 CALL                     0
                            182 STORE_FAST               3 (create)
                
-                92         184 LOAD_FAST                3 (create)
+                96         184 LOAD_FAST                3 (create)
                            186 LOAD_CONST               3 ('@context')
                            188 BINARY_SUBSCR
                
-                93         198 LOAD_CONST               4 ('as:Hashtag')
+                97         198 LOAD_CONST               4 ('as:Hashtag')
                            200 LOAD_CONST               5 ('as:sensitive')
                            202 LOAD_CONST               6 (('Hashtag', 'sensitive'))
                            204 BUILD_CONST_KEY_MAP      2
                
-                91         206 BUILD_LIST               2
+                95         206 BUILD_LIST               2
                            208 LOAD_FAST                3 (create)
                            210 LOAD_CONST               3 ('@context')
                            212 STORE_SUBSCR
                
-                95         216 LOAD_FAST                3 (create)
+                99         216 LOAD_FAST                3 (create)
                            218 LOAD_FAST                0 (self)
                            220 STORE_ATTR               5 (activity)
                
-                97         230 LOAD_FAST                0 (self)
+               101         230 LOAD_FAST                0 (self)
                            232 LOAD_ATTR                6 (bovine_actor)
                            242 LOAD_METHOD              7 (get)
                            264 LOAD_FAST                1 (remote)
                            266 PRECALL                  1
                            270 CALL                     1
                            280 GET_AWAITABLE            0
                            282 LOAD_CONST               7 (None)
@@ -433,133 +461,151 @@
                            286 YIELD_VALUE
                            288 RESUME                   3
                            290 JUMP_BACKWARD_NO_INTERRUPT     4 (to 284)
                        >>  292 LOAD_CONST               8 ('inbox')
                            294 BINARY_SUBSCR
                            304 STORE_FAST               4 (remote_inbox)
                
-                99         306 LOAD_FAST                0 (self)
-                           308 LOAD_ATTR                6 (bovine_actor)
-                           318 LOAD_METHOD              8 (post)
-                           340 LOAD_FAST                4 (remote_inbox)
-                           342 LOAD_FAST                3 (create)
-                           344 PRECALL                  2
-                           348 CALL                     2
+               103         306 LOAD_FAST                0 (self)
+                           308 LOAD_ATTR                8 (sleep_after_getting_inbox)
+                           318 POP_JUMP_FORWARD_IF_FALSE    26 (to 372)
+               
+               107         320 LOAD_GLOBAL             19 (NULL + asyncio)
+                           332 LOAD_ATTR               10 (sleep)
+                           342 LOAD_CONST               9 (0.1)
+                           344 PRECALL                  1
+                           348 CALL                     1
                            358 GET_AWAITABLE            0
                            360 LOAD_CONST               7 (None)
                        >>  362 SEND                     3 (to 370)
                            364 YIELD_VALUE
                            366 RESUME                   3
                            368 JUMP_BACKWARD_NO_INTERRUPT     4 (to 362)
-                       >>  370 RETURN_VALUE
-                       >>  372 PUSH_EXC_INFO
+                       >>  370 POP_TOP
                
-               100         374 LOAD_GLOBAL             18 (Exception)
-                           386 CHECK_EXC_MATCH
-                           388 POP_JUMP_FORWARD_IF_FALSE    52 (to 494)
-                           390 STORE_FAST               5 (e)
-               
-               101         392 LOAD_GLOBAL             20 (logger)
-                           404 LOAD_METHOD             11 (warning)
-                           426 LOAD_CONST               9 ('Posting to inbox of %s failed with %s')
-                           428 LOAD_FAST                1 (remote)
-                           430 LOAD_GLOBAL             25 (NULL + repr)
-                           442 LOAD_FAST                5 (e)
-                           444 PRECALL                  1
-                           448 CALL                     1
-                           458 PRECALL                  3
-                           462 CALL                     3
-                           472 POP_TOP
-               
-               102         474 POP_EXCEPT
-                           476 LOAD_CONST               7 (None)
-                           478 STORE_FAST               5 (e)
-                           480 DELETE_FAST              5 (e)
-                           482 LOAD_CONST               7 (None)
-                           484 RETURN_VALUE
-                       >>  486 LOAD_CONST               7 (None)
-                           488 STORE_FAST               5 (e)
-                           490 DELETE_FAST              5 (e)
-                           492 RERAISE                  1
-               
-               100     >>  494 RERAISE                  0
-                       >>  496 COPY                     3
-                           498 POP_EXCEPT
-                           500 RERAISE                  1
+               109     >>  372 LOAD_FAST                0 (self)
+                           374 LOAD_ATTR                6 (bovine_actor)
+                           384 LOAD_METHOD             11 (post)
+                           406 LOAD_FAST                4 (remote_inbox)
+                           408 LOAD_FAST                3 (create)
+                           410 PRECALL                  2
+                           414 CALL                     2
+                           424 GET_AWAITABLE            0
+                           426 LOAD_CONST               7 (None)
+                       >>  428 SEND                     3 (to 436)
+                           430 YIELD_VALUE
+                           432 RESUME                   3
+                           434 JUMP_BACKWARD_NO_INTERRUPT     4 (to 428)
+                       >>  436 RETURN_VALUE
+                       >>  438 PUSH_EXC_INFO
+               
+               110         440 LOAD_GLOBAL             24 (Exception)
+                           452 CHECK_EXC_MATCH
+                           454 POP_JUMP_FORWARD_IF_FALSE    52 (to 560)
+                           456 STORE_FAST               5 (e)
+               
+               111         458 LOAD_GLOBAL             26 (logger)
+                           470 LOAD_METHOD             14 (warning)
+                           492 LOAD_CONST              10 ('Posting to inbox of %s failed with %s')
+                           494 LOAD_FAST                1 (remote)
+                           496 LOAD_GLOBAL             31 (NULL + repr)
+                           508 LOAD_FAST                5 (e)
+                           510 PRECALL                  1
+                           514 CALL                     1
+                           524 PRECALL                  3
+                           528 CALL                     3
+                           538 POP_TOP
+               
+               112         540 POP_EXCEPT
+                           542 LOAD_CONST               7 (None)
+                           544 STORE_FAST               5 (e)
+                           546 DELETE_FAST              5 (e)
+                           548 LOAD_CONST               7 (None)
+                           550 RETURN_VALUE
+                       >>  552 LOAD_CONST               7 (None)
+                           554 STORE_FAST               5 (e)
+                           556 DELETE_FAST              5 (e)
+                           558 RERAISE                  1
+               
+               110     >>  560 RERAISE                  0
+                       >>  562 COPY                     3
+                           564 POP_EXCEPT
+                           566 RERAISE                  1
                ExceptionTable:
-                 8 to 368 -> 372 [0]
-                 372 to 390 -> 496 [1] lasti
-                 392 to 472 -> 486 [1] lasti
-                 486 to 494 -> 496 [1] lasti
+                 8 to 434 -> 438 [0]
+                 438 to 456 -> 562 [1] lasti
+                 458 to 538 -> 552 [1] lasti
+                 552 to 560 -> 562 [1] lasti
                consts
                   'Sends the activity to the remote user\n\n        :param remote: Actor URI of the remote user'
                   'to'
                   ('id',)
                   '@context'
                   'as:Hashtag'
                   'as:sensitive'
                   ('Hashtag', 'sensitive')
                   None
                   'inbox'
+                  0.1
                   'Posting to inbox of %s failed with %s'
-               names      ('note', 'activity_factory', 'create', 'make_id', 'build', 'activity', 'bovine_actor', 'get', 'post', 'Exception', 'logger', 'warning', 'repr')
+               names      ('note', 'activity_factory', 'create', 'make_id', 'build', 'activity', 'bovine_actor', 'get', 'sleep_after_getting_inbox', 'asyncio', 'sleep', 'post', 'Exception', 'logger', 'warning', 'repr')
                varnames   ('self', 'remote', 'note', 'create', 'remote_inbox', 'e')
                freevars   ()
                cellvars   ()
                filename   '/woodpecker/src/codeberg.org/funfedidev/python_fediverse_pasture/fediverse_pasture/runner/__init__.py'
                name       'send'
-               firstlineno 78
+               firstlineno 82
                lnotab
-                  0x0605020102010cff04031e0280030e0108fe0a040e024c024401120152
-                  0114fe
+                  0x0605020102010cff04031e0280030e0108fe0a040e024c020e04340244
+                  011201520114fe
             code
                argcount  : 2
                nlocals   : 5
                stacksize : 6
                flags     : 3
                code
                   0x870197007401000000000000000000008901a001000000000000000000
                   0000000000000000000000a6000000ab000000000000000000a6010000ab
                   0100000000000000005c0200007d027d0388016601640184087d04740500
                   0000000000000000007c027c037c007c04ac02a6040000ab040000000000
                   0000005300
                              0 MAKE_CELL                1 (actor_object)
                
-               104           2 RESUME                   0
+               114           2 RESUME                   0
                
-               108           4 LOAD_GLOBAL              1 (NULL + factories_for_actor_object)
+               118           4 LOAD_GLOBAL              1 (NULL + factories_for_actor_object)
                
-               109          16 LOAD_DEREF               1 (actor_object)
+               119          16 LOAD_DEREF               1 (actor_object)
                             18 LOAD_METHOD              1 (build)
                             40 PRECALL                  0
                             44 CALL                     0
                
-               108          54 PRECALL                  1
+               118          54 PRECALL                  1
                             58 CALL                     1
                             68 UNPACK_SEQUENCE          2
                             72 STORE_FAST               2 (activity_factory)
                             74 STORE_FAST               3 (object_factory)
                
-               112          76 LOAD_CLOSURE             1 (actor_object)
+               122          76 LOAD_CLOSURE             1 (actor_object)
                             78 BUILD_TUPLE              1
-                            80 LOAD_CONST               1 (<code object make_id, file "/woodpecker/src/codeberg.org/funfedidev/python_fediverse_pasture/fediverse_pasture/runner/__init__.py", line 112>)
+                            80 LOAD_CONST               1 (<code object make_id, file "/woodpecker/src/codeberg.org/funfedidev/python_fediverse_pasture/fediverse_pasture/runner/__init__.py", line 122>)
                             82 MAKE_FUNCTION            8 (closure)
                             84 STORE_FAST               4 (make_id)
                
-               115          86 LOAD_GLOBAL              5 (NULL + ActivitySender)
+               125          86 LOAD_GLOBAL              5 (NULL + ActivitySender)
                
-               116          98 LOAD_FAST                2 (activity_factory)
+               126          98 LOAD_FAST                2 (activity_factory)
                
-               117         100 LOAD_FAST                3 (object_factory)
+               127         100 LOAD_FAST                3 (object_factory)
                
-               118         102 LOAD_FAST                0 (bovine_actor)
+               128         102 LOAD_FAST                0 (bovine_actor)
                
-               119         104 LOAD_FAST                4 (make_id)
+               129         104 LOAD_FAST                4 (make_id)
                
-               115         106 KW_NAMES                 2
+               125         106 KW_NAMES                 2
                            108 PRECALL                  4
                            112 CALL                     4
                            122 RETURN_VALUE
                consts
                   'Initializes the Activity Sender object for a given BovineActor\n        and the corresponding actor object'
                   code
                      argcount  : 0
@@ -567,17 +613,17 @@
                      stacksize : 4
                      flags     : 19
                      code
                         0x9501970089006a00000000000000000064017a00000074030000000000
                         00000000006402a6010000ab0100000000000000007a0000005300
                                    0 COPY_FREE_VARS           1
                      
-                     112           2 RESUME                   0
+                     122           2 RESUME                   0
                      
-                     113           4 LOAD_DEREF               0 (actor_object)
+                     123           4 LOAD_DEREF               0 (actor_object)
                                    6 LOAD_ATTR                0 (id)
                                   16 LOAD_CONST               1 ('/')
                                   18 BINARY_OP                0 (+)
                                   22 LOAD_GLOBAL              3 (NULL + token_urlsafe)
                                   34 LOAD_CONST               2 (8)
                                   36 PRECALL                  1
                                   40 CALL                     1
@@ -589,167 +635,259 @@
                         8
                      names      ('id', 'token_urlsafe')
                      varnames   ()
                      freevars   ('actor_object',)
                      cellvars   ()
                      filename   '/woodpecker/src/codeberg.org/funfedidev/python_fediverse_pasture/fediverse_pasture/runner/__init__.py'
                      name       'make_id'
-                     firstlineno 112
+                     firstlineno 122
                      lnotab 0x0401
                   ('activity_factory', 'object_factory', 'bovine_actor', 'make_id')
                names      ('factories_for_actor_object', 'build', 'ActivitySender')
                varnames   ('bovine_actor', 'actor_object', 'activity_factory', 'object_factory', 'make_id')
                freevars   ()
                cellvars   ('actor_object',)
                filename   '/woodpecker/src/codeberg.org/funfedidev/python_fediverse_pasture/fediverse_pasture/runner/__init__.py'
                name       'for_actor'
-               firstlineno 104
+               firstlineno 114
                lnotab 0x04040c0126ff16040a030c0102010201020102fc
-         names      ('__name__', '__module__', '__qualname__', '__doc__', 'ActivityFactory', '__annotations__', 'ObjectFactory', 'BovineActor', 'Callable', 'published', 'datetime', 'note', 'dict', 'activity', 'init_create_note', 'str', 'send', 'staticmethod', 'for_actor')
+         names      ('__name__', '__module__', '__qualname__', '__doc__', 'ActivityFactory', '__annotations__', 'ObjectFactory', 'BovineActor', 'Callable', 'published', 'datetime', 'note', 'dict', 'activity', 'object_id', 'str', 'sleep_after_getting_inbox', 'bool', 'init_create_note', 'send', 'staticmethod', 'for_actor')
          varnames   ()
          freevars   ()
          cellvars   ()
          filename   '/woodpecker/src/codeberg.org/funfedidev/python_fediverse_pasture/fediverse_pasture/runner/__init__.py'
          name       'ActivitySender'
          firstlineno 26
-         lnotab 0x0c0204110a010a010a010a021401140114021e180c1a020104ff0e01
+         lnotab
+            0x0c0204110a010a010a010a0214011401140114020e021e190c20020104
+            ff0e01
       'ActivitySender'
       code
          argcount  : 0
          nlocals   : 0
-         stacksize : 5
+         stacksize : 4
          flags     : 0
          code
             0x970065005a0164005a02550064015a036504650564023c000000650665
-            0719000000000000000000650564033c0000000900640964056508650967
-            0165096602190000000000000000006406650a6604640784055a0b640853
+            0719000000000000000000650564033c00000064045a086509650564053c
+            000000090064065a0a650b650564073c0000000900640884005a0c640965
+            0d650e6701650e6602190000000000000000006602640a84045a0f640b53
             00
-         123           0 RESUME                   0
+         133           0 RESUME                   0
                        2 LOAD_NAME                0 (__name__)
                        4 STORE_NAME               1 (__module__)
                        6 LOAD_CONST               0 ('ActivityRunner')
                        8 STORE_NAME               2 (__qualname__)
                       10 SETUP_ANNOTATIONS
          
-         125          12 LOAD_CONST               1 ('Coordinates sending an activity to many applications through an ActivitySender\n    instances\n\n    :param activity_sender: an activity sender\n    :param applications: list of applications to run against')
+         135          12 LOAD_CONST               1 ('Coordinates sending an activity to many applications through an ActivitySender\n    instances\n\n    :param activity_sender: an activity sender\n    :param applications: list of applications to run against')
                       14 STORE_NAME               3 (__doc__)
          
-         131          16 LOAD_NAME                4 (ActivitySender)
+         141          16 LOAD_NAME                4 (ActivitySender)
                       18 LOAD_NAME                5 (__annotations__)
                       20 LOAD_CONST               2 ('activity_sender')
                       22 STORE_SUBSCR
          
-         132          26 LOAD_NAME                6 (List)
+         142          26 LOAD_NAME                6 (List)
                       28 LOAD_NAME                7 (ApplicationAdapterForLastActivity)
                       30 BINARY_SUBSCR
                       40 LOAD_NAME                5 (__annotations__)
                       42 LOAD_CONST               3 ('applications')
                       44 STORE_SUBSCR
          
-         135          48 NOP
-         
-         134          50 LOAD_CONST               9 ((2.0,))
-                      52 LOAD_CONST               5 ('modifier')
-         
-         135          54 LOAD_NAME                8 (Callable)
-                      56 LOAD_NAME                9 (dict)
-                      58 BUILD_LIST               1
-                      60 LOAD_NAME                9 (dict)
-                      62 BUILD_TUPLE              2
-                      64 BINARY_SUBSCR
-         
-         134          74 LOAD_CONST               6 ('wait_time')
-         
-         135          76 LOAD_NAME               10 (float)
-         
-         134          78 BUILD_TUPLE              4
-                      80 LOAD_CONST               7 (<code object run_for_modifier, file "/woodpecker/src/codeberg.org/funfedidev/python_fediverse_pasture/fediverse_pasture/runner/__init__.py", line 134>)
-                      82 MAKE_FUNCTION            5 (defaults, annotations)
-                      84 STORE_NAME              11 (run_for_modifier)
-                      86 LOAD_CONST               8 (None)
-                      88 RETURN_VALUE
+         144          48 LOAD_CONST               4 (0.5)
+                      50 STORE_NAME               8 (wait_time)
+                      52 LOAD_NAME                9 (float)
+                      54 LOAD_NAME                5 (__annotations__)
+                      56 LOAD_CONST               5 ('wait_time')
+                      58 STORE_SUBSCR
+         
+         145          62 NOP
+         
+         147          64 LOAD_CONST               6 (20)
+                      66 STORE_NAME              10 (tries)
+                      68 LOAD_NAME               11 (int)
+                      70 LOAD_NAME                5 (__annotations__)
+                      72 LOAD_CONST               7 ('tries')
+                      74 STORE_SUBSCR
+         
+         148          78 NOP
+         
+         150          80 LOAD_CONST               8 (<code object fetch_activity, file "/woodpecker/src/codeberg.org/funfedidev/python_fediverse_pasture/fediverse_pasture/runner/__init__.py", line 150>)
+                      82 MAKE_FUNCTION            0
+                      84 STORE_NAME              12 (fetch_activity)
+         
+         157          86 LOAD_CONST               9 ('modifier')
+                      88 LOAD_NAME               13 (Callable)
+                      90 LOAD_NAME               14 (dict)
+                      92 BUILD_LIST               1
+                      94 LOAD_NAME               14 (dict)
+                      96 BUILD_TUPLE              2
+                      98 BINARY_SUBSCR
+                     108 BUILD_TUPLE              2
+                     110 LOAD_CONST              10 (<code object run_for_modifier, file "/woodpecker/src/codeberg.org/funfedidev/python_fediverse_pasture/fediverse_pasture/runner/__init__.py", line 157>)
+                     112 MAKE_FUNCTION            4 (annotations)
+                     114 STORE_NAME              15 (run_for_modifier)
+                     116 LOAD_CONST              11 (None)
+                     118 RETURN_VALUE
          consts
             'ActivityRunner'
             'Coordinates sending an activity to many applications through an ActivitySender\n    instances\n\n    :param activity_sender: an activity sender\n    :param applications: list of applications to run against'
             'activity_sender'
             'applications'
-            2.0
-            'modifier'
+            0.5
             'wait_time'
+            20
+            'tries'
             code
                argcount  : 3
-               nlocals   : 6
+               nlocals   : 5
+               stacksize : 4
+               flags     : 131
+               code
+                  0x4b00010097007401000000000000000000007c006a0100000000000000
+                  00a6010000ab01000000000000000044005d427d037c01a0020000000000
+                  0000000000000000000000000000007c02a6010000ab0100000000000000
+                  00830064007b035600970386047d047c0472047c04630201005300740700
+                  0000000000000000006a0400000000000000007c006a0500000000000000
+                  00a6010000ab010000000000000000830064007b0356009703860401008c
+                  4364005300
+               150           0 RETURN_GENERATOR
+                             2 POP_TOP
+                             4 RESUME                   0
+               
+               151           6 LOAD_GLOBAL              1 (NULL + range)
+                            18 LOAD_FAST                0 (self)
+                            20 LOAD_ATTR                1 (tries)
+                            30 PRECALL                  1
+                            34 CALL                     1
+                            44 GET_ITER
+                       >>   46 FOR_ITER                66 (to 180)
+                            48 STORE_FAST               3 (_)
+               
+               152          50 LOAD_FAST                1 (application)
+                            52 LOAD_METHOD              2 (fetch_activity)
+                            74 LOAD_FAST                2 (object_id)
+                            76 PRECALL                  1
+                            80 CALL                     1
+                            90 GET_AWAITABLE            0
+                            92 LOAD_CONST               0 (None)
+                       >>   94 SEND                     3 (to 102)
+                            96 YIELD_VALUE
+                            98 RESUME                   3
+                           100 JUMP_BACKWARD_NO_INTERRUPT     4 (to 94)
+                       >>  102 STORE_FAST               4 (result)
+               
+               153         104 LOAD_FAST                4 (result)
+                           106 POP_JUMP_FORWARD_IF_FALSE     4 (to 116)
+               
+               154         108 LOAD_FAST                4 (result)
+                           110 SWAP                     2
+                           112 POP_TOP
+                           114 RETURN_VALUE
+               
+               155     >>  116 LOAD_GLOBAL              7 (NULL + asyncio)
+                           128 LOAD_ATTR                4 (sleep)
+                           138 LOAD_FAST                0 (self)
+                           140 LOAD_ATTR                5 (wait_time)
+                           150 PRECALL                  1
+                           154 CALL                     1
+                           164 GET_AWAITABLE            0
+                           166 LOAD_CONST               0 (None)
+                       >>  168 SEND                     3 (to 176)
+                           170 YIELD_VALUE
+                           172 RESUME                   3
+                           174 JUMP_BACKWARD_NO_INTERRUPT     4 (to 168)
+                       >>  176 POP_TOP
+                           178 JUMP_BACKWARD           67 (to 46)
+               
+               151     >>  180 LOAD_CONST               0 (None)
+                           182 RETURN_VALUE
+               consts
+                  None
+               names      ('range', 'tries', 'fetch_activity', 'asyncio', 'sleep', 'wait_time')
+               varnames   ('self', 'application', 'object_id', '_', 'result')
+               freevars   ()
+               cellvars   ()
+               filename   '/woodpecker/src/codeberg.org/funfedidev/python_fediverse_pasture/fediverse_pasture/runner/__init__.py'
+               name       'fetch_activity'
+               firstlineno 150
+               lnotab 0x06012c0136010401080140fc
+            'modifier'
+            code
+               argcount  : 2
+               nlocals   : 5
                stacksize : 7
                flags     : 131
                code
                   0x4b00010097007c006a000000000000000000a001000000000000000000
                   00000000000000000000007c01a6010000ab010000000000000000010074
                   05000000000000000000006a030000000000000000a6000000ab00000000
-                  00000000003400830164017b035600970386047d037c006a040000000000
-                  00000044005d347d047c03a0050000000000000000000000000000000000
+                  00000000003400830164017b035600970386047d027c006a040000000000
+                  00000044005d347d037c02a0050000000000000000000000000000000000
                   0000007c006a000000000000000000a00600000000000000000000000000
-                  000000000000007c046a070000000000000000a6010000ab010000000000
+                  000000000000007c036a070000000000000000a6010000ab010000000000
                   000000a6010000ab01000000000000000001008c350900640164016401a6
                   020000ab020000000000000000830264017b0356009703860401006e1123
                   003100830264017b03560097038604730477027803590077010100590001
-                  0001007405000000000000000000006a0800000000000000007c02a60100
-                  00ab010000000000000000830064017b03560097038604010064027c006a
-                  0000000000000000006a09000000000000000069017d057c006a04000000
-                  000000000044005d2f7d047c04a00a000000000000000000000000000000
-                  00000000007c006a0000000000000000006a0b0000000000000000a60100
-                  00ab010000000000000000830064017b035600970386047c057c046a0c00
-                  000000000000003c0000008c307c055300
-               134           0 RETURN_GENERATOR
+                  0001007405000000000000000000006a0800000000000000007c006a0900
+                  00000000000000a6010000ab010000000000000000830064017b03560097
+                  038604010064027c006a0000000000000000006a0a000000000000000069
+                  017d047c006a04000000000000000044005d307d037c00a00b0000000000
+                  0000000000000000000000000000007c037c006a0000000000000000006a
+                  0c0000000000000000a6020000ab020000000000000000830064017b0356
+                  00970386047c047c036a0d00000000000000003c0000008c317c045300
+               157           0 RETURN_GENERATOR
                              2 POP_TOP
                              4 RESUME                   0
                
-               138           6 LOAD_FAST                0 (self)
+               161           6 LOAD_FAST                0 (self)
                              8 LOAD_ATTR                0 (activity_sender)
                             18 LOAD_METHOD              1 (init_create_note)
                             40 LOAD_FAST                1 (modifier)
                             42 PRECALL                  1
                             46 CALL                     1
                             56 POP_TOP
                
-               140          58 LOAD_GLOBAL              5 (NULL + asyncio)
+               163          58 LOAD_GLOBAL              5 (NULL + asyncio)
                             70 LOAD_ATTR                3 (TaskGroup)
                             80 PRECALL                  0
                             84 CALL                     0
                             94 BEFORE_ASYNC_WITH
                             96 GET_AWAITABLE            1
                             98 LOAD_CONST               1 (None)
                        >>  100 SEND                     3 (to 108)
                            102 YIELD_VALUE
                            104 RESUME                   3
                            106 JUMP_BACKWARD_NO_INTERRUPT     4 (to 100)
-                       >>  108 STORE_FAST               3 (tg)
+                       >>  108 STORE_FAST               2 (tg)
                
-               141         110 LOAD_FAST                0 (self)
+               164         110 LOAD_FAST                0 (self)
                            112 LOAD_ATTR                4 (applications)
                            122 GET_ITER
                        >>  124 FOR_ITER                52 (to 230)
-                           126 STORE_FAST               4 (application)
+                           126 STORE_FAST               3 (application)
                
-               142         128 LOAD_FAST                3 (tg)
+               165         128 LOAD_FAST                2 (tg)
                            130 LOAD_METHOD              5 (create_task)
                            152 LOAD_FAST                0 (self)
                            154 LOAD_ATTR                0 (activity_sender)
                            164 LOAD_METHOD              6 (send)
-                           186 LOAD_FAST                4 (application)
+                           186 LOAD_FAST                3 (application)
                            188 LOAD_ATTR                7 (actor_uri)
                            198 PRECALL                  1
                            202 CALL                     1
                            212 PRECALL                  1
                            216 CALL                     1
                            226 POP_TOP
                            228 JUMP_BACKWARD           53 (to 124)
                
-               141     >>  230 NOP
+               164     >>  230 NOP
                
-               140         232 LOAD_CONST               1 (None)
+               163         232 LOAD_CONST               1 (None)
                            234 LOAD_CONST               1 (None)
                            236 LOAD_CONST               1 (None)
                            238 PRECALL                  2
                            242 CALL                     2
                            252 GET_AWAITABLE            2
                            254 LOAD_CONST               1 (None)
                        >>  256 SEND                     3 (to 264)
@@ -772,93 +910,94 @@
                            290 POP_EXCEPT
                            292 RERAISE                  1
                        >>  294 POP_TOP
                            296 POP_EXCEPT
                            298 POP_TOP
                            300 POP_TOP
                
-               143     >>  302 LOAD_GLOBAL              5 (NULL + asyncio)
+               166     >>  302 LOAD_GLOBAL              5 (NULL + asyncio)
                            314 LOAD_ATTR                8 (sleep)
-                           324 LOAD_FAST                2 (wait_time)
-                           326 PRECALL                  1
-                           330 CALL                     1
-                           340 GET_AWAITABLE            0
-                           342 LOAD_CONST               1 (None)
-                       >>  344 SEND                     3 (to 352)
-                           346 YIELD_VALUE
-                           348 RESUME                   3
-                           350 JUMP_BACKWARD_NO_INTERRUPT     4 (to 344)
-                       >>  352 POP_TOP
-               
-               145         354 LOAD_CONST               2 ('activity')
-                           356 LOAD_FAST                0 (self)
-                           358 LOAD_ATTR                0 (activity_sender)
-                           368 LOAD_ATTR                9 (activity)
-                           378 BUILD_MAP                1
-                           380 STORE_FAST               5 (result)
-               
-               147         382 LOAD_FAST                0 (self)
-                           384 LOAD_ATTR                4 (applications)
-                           394 GET_ITER
-                       >>  396 FOR_ITER                47 (to 492)
-                           398 STORE_FAST               4 (application)
-               
-               148         400 LOAD_FAST                4 (application)
-                           402 LOAD_METHOD             10 (fetch_activity)
-               
-               149         424 LOAD_FAST                0 (self)
-                           426 LOAD_ATTR                0 (activity_sender)
-                           436 LOAD_ATTR               11 (published)
-               
-               148         446 PRECALL                  1
-                           450 CALL                     1
-                           460 GET_AWAITABLE            0
-                           462 LOAD_CONST               1 (None)
-                       >>  464 SEND                     3 (to 472)
-                           466 YIELD_VALUE
-                           468 RESUME                   3
-                           470 JUMP_BACKWARD_NO_INTERRUPT     4 (to 464)
-                       >>  472 LOAD_FAST                5 (result)
-                           474 LOAD_FAST                4 (application)
-                           476 LOAD_ATTR               12 (application_name)
-                           486 STORE_SUBSCR
-                           490 JUMP_BACKWARD           48 (to 396)
+                           324 LOAD_FAST                0 (self)
+                           326 LOAD_ATTR                9 (wait_time)
+                           336 PRECALL                  1
+                           340 CALL                     1
+                           350 GET_AWAITABLE            0
+                           352 LOAD_CONST               1 (None)
+                       >>  354 SEND                     3 (to 362)
+                           356 YIELD_VALUE
+                           358 RESUME                   3
+                           360 JUMP_BACKWARD_NO_INTERRUPT     4 (to 354)
+                       >>  362 POP_TOP
+               
+               168         364 LOAD_CONST               2 ('activity')
+                           366 LOAD_FAST                0 (self)
+                           368 LOAD_ATTR                0 (activity_sender)
+                           378 LOAD_ATTR               10 (activity)
+                           388 BUILD_MAP                1
+                           390 STORE_FAST               4 (result)
+               
+               170         392 LOAD_FAST                0 (self)
+                           394 LOAD_ATTR                4 (applications)
+                           404 GET_ITER
+                       >>  406 FOR_ITER                48 (to 504)
+                           408 STORE_FAST               3 (application)
+               
+               171         410 LOAD_FAST                0 (self)
+                           412 LOAD_METHOD             11 (fetch_activity)
+               
+               172         434 LOAD_FAST                3 (application)
+                           436 LOAD_FAST                0 (self)
+                           438 LOAD_ATTR                0 (activity_sender)
+                           448 LOAD_ATTR               12 (object_id)
+               
+               171         458 PRECALL                  2
+                           462 CALL                     2
+                           472 GET_AWAITABLE            0
+                           474 LOAD_CONST               1 (None)
+                       >>  476 SEND                     3 (to 484)
+                           478 YIELD_VALUE
+                           480 RESUME                   3
+                           482 JUMP_BACKWARD_NO_INTERRUPT     4 (to 476)
+                       >>  484 LOAD_FAST                4 (result)
+                           486 LOAD_FAST                3 (application)
+                           488 LOAD_ATTR               13 (application_name)
+                           498 STORE_SUBSCR
+                           502 JUMP_BACKWARD           49 (to 406)
                
-               152     >>  492 LOAD_FAST                5 (result)
-                           494 RETURN_VALUE
+               175     >>  504 LOAD_FAST                4 (result)
+                           506 RETURN_VALUE
                ExceptionTable:
                  108 to 228 -> 268 [1] lasti
                  268 to 286 -> 288 [3] lasti
                  294 to 294 -> 288 [3] lasti
                consts
-                  'modifier has the same format as for ActivitySender'
+                  'modifier has the same format as for ActivitySender\n\n        :param modifier: modifies the base object being send'
                   None
                   'activity'
-               names      ('activity_sender', 'init_create_note', 'asyncio', 'TaskGroup', 'applications', 'create_task', 'send', 'actor_uri', 'sleep', 'activity', 'fetch_activity', 'published', 'application_name')
-               varnames   ('self', 'modifier', 'wait_time', 'tg', 'application', 'result')
+               names      ('activity_sender', 'init_create_note', 'asyncio', 'TaskGroup', 'applications', 'create_task', 'send', 'actor_uri', 'sleep', 'wait_time', 'activity', 'fetch_activity', 'object_id', 'application_name')
+               varnames   ('self', 'modifier', 'tg', 'application', 'result')
                freevars   ()
                cellvars   ()
                filename   '/woodpecker/src/codeberg.org/funfedidev/python_fediverse_pasture/fediverse_pasture/runner/__init__.py'
                name       'run_for_modifier'
-               firstlineno 134
-               lnotab 0x060434023401120166ff02ff460334021c021201180116ff2e04
+               firstlineno 157
+               lnotab 0x060434023401120166ff02ff46033e021c021201180118ff2e04
             None
-            (2.0,)
-         names      ('__name__', '__module__', '__qualname__', '__doc__', 'ActivitySender', '__annotations__', 'List', 'ApplicationAdapterForLastActivity', 'Callable', 'dict', 'float', 'run_for_modifier')
+         names      ('__name__', '__module__', '__qualname__', '__doc__', 'ActivitySender', '__annotations__', 'List', 'ApplicationAdapterForLastActivity', 'wait_time', 'float', 'tries', 'int', 'fetch_activity', 'Callable', 'dict', 'run_for_modifier')
          varnames   ()
          freevars   ()
          cellvars   ()
          filename   '/woodpecker/src/codeberg.org/funfedidev/python_fediverse_pasture/fediverse_pasture/runner/__init__.py'
          name       'ActivityRunner'
-         firstlineno 123
-         lnotab 0x0c0204060a01160302ff040114ff020102ff
+         firstlineno 133
+         lnotab 0x0c0204060a0116020e0102020e0102020607
       'ActivityRunner'
    names      ('asyncio', 'logging', 'dataclasses', 'dataclass', 'datetime', 'typing', 'Callable', 'List', 'secrets', 'token_urlsafe', 'bovine', 'BovineActor', 'bovine.activitystreams', 'ActivityFactory', 'ObjectFactory', 'factories_for_actor_object', 'bovine.utils', 'now_isoformat', 'fediverse_pasture.types', 'ApplicationAdapterForLastActivity', 'getLogger', '__name__', 'logger', 'ActivitySender', 'ActivityRunner')
    varnames   ()
    freevars   ()
    cellvars   ()
    filename   '/woodpecker/src/codeberg.org/funfedidev/python_fediverse_pasture/fediverse_pasture/runner/__init__.py'
    name       '<module>'
    firstlineno 1
    lnotab
       0x00ff0205080108020c010c0110010c020c0114050c020c022003020118
-      ff0e010260020118ff0e01
+      ff0e01026a020118ff0e01
```

### Comparing `fediverse_pasture-0.2.8/fediverse_pasture/runner/__pycache__/entry.cpython-311.pyc` & `fediverse_pasture-0.2.9/fediverse_pasture/runner/__pycache__/entry.cpython-311.pyc`

 * *Files 1% similar despite different names*

#### Python bytecode

```diff
@@ -1,9 +1,9 @@
 magic:    0xa70d0d0a
-moddate:  0xf44def65 (Mon Mar 11 18:31:16 2024 UTC)
+moddate:  0xa6340966 (Sun Mar 31 10:02:14 2024 UTC)
 files sz: 3096
 code
    argcount  : 0
    nlocals   : 0
    stacksize : 5
    flags     : 0
    code
```

### Comparing `fediverse_pasture-0.2.8/fediverse_pasture/runner/__pycache__/models.cpython-311.pyc` & `fediverse_pasture-0.2.9/fediverse_pasture/runner/__pycache__/models.cpython-311.pyc`

 * *Files 12% similar despite different names*

#### Python bytecode

```diff
@@ -1,9 +1,9 @@
 magic:    0xa70d0d0a
-moddate:  0xf44def65 (Mon Mar 11 18:31:16 2024 UTC)
+moddate:  0xa6340966 (Sun Mar 31 10:02:14 2024 UTC)
 files sz: 410
 code
    argcount  : 0
    nlocals   : 0
    stacksize : 5
    flags     : 0
    code
```

### Comparing `fediverse_pasture-0.2.8/fediverse_pasture/runner/__pycache__/result_store.cpython-311.pyc` & `fediverse_pasture-0.2.9/fediverse_pasture/runner/__pycache__/result_store.cpython-311.pyc`

 * *Files 0% similar despite different names*

#### Python bytecode

```diff
@@ -1,9 +1,9 @@
 magic:    0xa70d0d0a
-moddate:  0xf44def65 (Mon Mar 11 18:31:16 2024 UTC)
+moddate:  0xa6340966 (Sun Mar 31 10:02:14 2024 UTC)
 files sz: 4129
 code
    argcount  : 0
    nlocals   : 0
    stacksize : 6
    flags     : 0
    code
```

### Comparing `fediverse_pasture-0.2.8/fediverse_pasture/runner/__pycache__/test_activity_sender.cpython-311-pytest-8.1.1.pyc` & `fediverse_pasture-0.2.9/fediverse_pasture/runner/__pycache__/test_activity_sender.cpython-311-pytest-8.1.1.pyc`

 * *Files 0% similar despite different names*

#### Python bytecode

```diff
@@ -1,9 +1,9 @@
 magic:    0xa70d0d0a
-moddate:  0xf44def65 (Mon Mar 11 18:31:16 2024 UTC)
+moddate:  0xa6340966 (Sun Mar 31 10:02:14 2024 UTC)
 files sz: 1808
 code
    argcount  : 0
    nlocals   : 0
    stacksize : 2
    flags     : 0
    code
```

### Comparing `fediverse_pasture-0.2.8/fediverse_pasture/runner/__pycache__/test_entry.cpython-311-pytest-8.1.1.pyc` & `fediverse_pasture-0.2.9/fediverse_pasture/runner/__pycache__/test_entry.cpython-311-pytest-8.1.1.pyc`

 * *Files 0% similar despite different names*

#### Python bytecode

```diff
@@ -1,9 +1,9 @@
 magic:    0xa70d0d0a
-moddate:  0xf44def65 (Mon Mar 11 18:31:16 2024 UTC)
+moddate:  0xa6340966 (Sun Mar 31 10:02:14 2024 UTC)
 files sz: 1134
 code
    argcount  : 0
    nlocals   : 0
    stacksize : 2
    flags     : 0
    code
```

### Comparing `fediverse_pasture-0.2.8/fediverse_pasture/runner/__pycache__/test_result_store.cpython-311-pytest-8.1.1.pyc` & `fediverse_pasture-0.2.9/fediverse_pasture/runner/__pycache__/test_result_store.cpython-311-pytest-8.1.1.pyc`

 * *Files 0% similar despite different names*

#### Python bytecode

```diff
@@ -1,9 +1,9 @@
 magic:    0xa70d0d0a
-moddate:  0xf44def65 (Mon Mar 11 18:31:16 2024 UTC)
+moddate:  0xa6340966 (Sun Mar 31 10:02:14 2024 UTC)
 files sz: 1652
 code
    argcount  : 0
    nlocals   : 0
    stacksize : 2
    flags     : 0
    code
```

### Comparing `fediverse_pasture-0.2.8/fediverse_pasture/runner/__pycache__/test_verify_actor.cpython-311-pytest-8.1.1.pyc` & `fediverse_pasture-0.2.9/fediverse_pasture/runner/__pycache__/test_verify_actor.cpython-311-pytest-8.1.1.pyc`

 * *Files 0% similar despite different names*

#### Python bytecode

```diff
@@ -1,9 +1,9 @@
 magic:    0xa70d0d0a
-moddate:  0xf44def65 (Mon Mar 11 18:31:16 2024 UTC)
+moddate:  0xa6340966 (Sun Mar 31 10:02:14 2024 UTC)
 files sz: 1592
 code
    argcount  : 0
    nlocals   : 0
    stacksize : 2
    flags     : 0
    code
```

### Comparing `fediverse_pasture-0.2.8/fediverse_pasture/runner/__pycache__/verify_actor.cpython-311.pyc` & `fediverse_pasture-0.2.9/fediverse_pasture/runner/__pycache__/verify_actor.cpython-311.pyc`

 * *Files 2% similar despite different names*

#### Python bytecode

```diff
@@ -1,9 +1,9 @@
 magic:    0xa70d0d0a
-moddate:  0xf44def65 (Mon Mar 11 18:31:16 2024 UTC)
+moddate:  0xa6340966 (Sun Mar 31 10:02:14 2024 UTC)
 files sz: 2712
 code
    argcount  : 0
    nlocals   : 0
    stacksize : 5
    flags     : 0
    code
```

### Comparing `fediverse_pasture-0.2.8/fediverse_pasture/runner/application/__pycache__/__init__.cpython-311.pyc` & `fediverse_pasture-0.2.9/fediverse_pasture/runner/application/__pycache__/__init__.cpython-311.pyc`

 * *Files 23% similar despite different names*

#### Python bytecode

```diff
@@ -1,253 +1,253 @@
 magic:    0xa70d0d0a
-moddate:  0xf44def65 (Mon Mar 11 18:31:16 2024 UTC)
-files sz: 4874
+moddate:  0xa6340966 (Sun Mar 31 10:02:14 2024 UTC)
+files sz: 3655
 code
    argcount  : 0
    nlocals   : 0
    stacksize : 16
    flags     : 0
    code
-      0x9700640064016c005a00640064026c016d015a010100640064036c026d
-      035a036d045a040100640064046c056d065a060100640064056c076d085a
-      086d095a090100640664076c0a6d0b5a0b0100640664086c0c6d0d5a0d01
-      00640664096c0e6d0f5a0f0100640a6510640b6510640c65006a11000000
-      0000000000640d65086608640e84045a1209000900641a64116510641265
-      1064136510640c65006a110000000000000000640b651064146513640d65
-      09660e641584055a146411651064126510640c65006a1100000000000000
-      00640d65096608641684045a1509000900641a6411651064126510641365
-      10640b651064146513640d650365006a1100000000000000006701650465
-      0919000000000000000000660219000000000000000000660c641784055a
-      166411651064126510640d650365006a1100000000000000006701650465
-      09190000000000000000006602190000000000000000006606641884045a
-      17641984005a1864015300
+      0x9700640064016c005a00640064026c016d025a026d035a030100640064
+      036c046d055a050100640064046c066d075a076d085a080100640564066c
+      096d0a5a0a0100640564076c0b6d0c5a0c0100640564086c0d6d0e5a0e01
+      00640564096c0f6d105a100100640a6511640b6511640c65006a12000000
+      0000000000640d65076608640e84045a1309000900641a64116511641265
+      1164136511640c65006a120000000000000000640b651164146514640d65
+      08660e641584055a156411651164126511640c65006a1200000000000000
+      00640d65086608641684045a1609000900641a6411651164126511641365
+      11640b651164146514640d650265006a1200000000000000006701650365
+      0819000000000000000000660219000000000000000000660c641784055a
+      176411651164126511640d650265006a1200000000000000006701650365
+      08190000000000000000006602190000000000000000006606641884045a
+      18641984005a1964015300
      0           0 RESUME                   0
    
      5           2 LOAD_CONST               0 (0)
                  4 LOAD_CONST               1 (None)
                  6 IMPORT_NAME              0 (aiohttp)
                  8 STORE_NAME               0 (aiohttp)
    
      6          10 LOAD_CONST               0 (0)
-                12 LOAD_CONST               2 (('datetime',))
-                14 IMPORT_NAME              1 (datetime)
-                16 IMPORT_FROM              1 (datetime)
-                18 STORE_NAME               1 (datetime)
-                20 POP_TOP
-   
-     7          22 LOAD_CONST               0 (0)
-                24 LOAD_CONST               3 (('Callable', 'Awaitable'))
-                26 IMPORT_NAME              2 (typing)
-                28 IMPORT_FROM              3 (Callable)
-                30 STORE_NAME               3 (Callable)
-                32 IMPORT_FROM              4 (Awaitable)
-                34 STORE_NAME               4 (Awaitable)
+                12 LOAD_CONST               2 (('Callable', 'Awaitable'))
+                14 IMPORT_NAME              1 (typing)
+                16 IMPORT_FROM              2 (Callable)
+                18 STORE_NAME               2 (Callable)
+                20 IMPORT_FROM              3 (Awaitable)
+                22 STORE_NAME               3 (Awaitable)
+                24 POP_TOP
+   
+     7          26 LOAD_CONST               0 (0)
+                28 LOAD_CONST               3 (('lookup_uri_with_webfinger',))
+                30 IMPORT_NAME              4 (bovine.clients)
+                32 IMPORT_FROM              5 (lookup_uri_with_webfinger)
+                34 STORE_NAME               5 (lookup_uri_with_webfinger)
                 36 POP_TOP
    
-     8          38 LOAD_CONST               0 (0)
-                40 LOAD_CONST               4 (('lookup_uri_with_webfinger',))
-                42 IMPORT_NAME              5 (bovine.clients)
-                44 IMPORT_FROM              6 (lookup_uri_with_webfinger)
-                46 STORE_NAME               6 (lookup_uri_with_webfinger)
-                48 POP_TOP
-   
-    10          50 LOAD_CONST               0 (0)
-                52 LOAD_CONST               5 (('ApplicationAdapterForActor', 'ApplicationAdapterForLastActivity'))
-                54 IMPORT_NAME              7 (fediverse_pasture.types)
-                56 IMPORT_FROM              8 (ApplicationAdapterForActor)
-                58 STORE_NAME               8 (ApplicationAdapterForActor)
-                60 IMPORT_FROM              9 (ApplicationAdapterForLastActivity)
-                62 STORE_NAME               9 (ApplicationAdapterForLastActivity)
+     9          38 LOAD_CONST               0 (0)
+                40 LOAD_CONST               4 (('ApplicationAdapterForActor', 'ApplicationAdapterForLastActivity'))
+                42 IMPORT_NAME              6 (fediverse_pasture.types)
+                44 IMPORT_FROM              7 (ApplicationAdapterForActor)
+                46 STORE_NAME               7 (ApplicationAdapterForActor)
+                48 IMPORT_FROM              8 (ApplicationAdapterForLastActivity)
+                50 STORE_NAME               8 (ApplicationAdapterForLastActivity)
+                52 POP_TOP
+   
+    15          54 LOAD_CONST               5 (1)
+                56 LOAD_CONST               6 (('MastodonApplication',))
+                58 IMPORT_NAME              9 (mastodon)
+                60 IMPORT_FROM             10 (MastodonApplication)
+                62 STORE_NAME              10 (MastodonApplication)
                 64 POP_TOP
    
-    16          66 LOAD_CONST               6 (1)
-                68 LOAD_CONST               7 (('MastodonApplication',))
-                70 IMPORT_NAME             10 (mastodon)
-                72 IMPORT_FROM             11 (MastodonApplication)
-                74 STORE_NAME              11 (MastodonApplication)
+    16          66 LOAD_CONST               5 (1)
+                68 LOAD_CONST               7 (('MisskeyApplication',))
+                70 IMPORT_NAME             11 (misskey)
+                72 IMPORT_FROM             12 (MisskeyApplication)
+                74 STORE_NAME              12 (MisskeyApplication)
                 76 POP_TOP
    
-    17          78 LOAD_CONST               6 (1)
+    17          78 LOAD_CONST               5 (1)
                 80 LOAD_CONST               8 (('FirefishApplication',))
-                82 IMPORT_NAME             12 (firefish)
-                84 IMPORT_FROM             13 (FirefishApplication)
-                86 STORE_NAME              13 (FirefishApplication)
+                82 IMPORT_NAME             13 (firefish)
+                84 IMPORT_FROM             14 (FirefishApplication)
+                86 STORE_NAME              14 (FirefishApplication)
                 88 POP_TOP
    
-    18          90 LOAD_CONST               6 (1)
+    18          90 LOAD_CONST               5 (1)
                 92 LOAD_CONST               9 (('BovineApplication',))
-                94 IMPORT_NAME             14 (bovine)
-                96 IMPORT_FROM             15 (BovineApplication)
-                98 STORE_NAME              15 (BovineApplication)
+                94 IMPORT_NAME             15 (bovine)
+                96 IMPORT_FROM             16 (BovineApplication)
+                98 STORE_NAME              16 (BovineApplication)
                100 POP_TOP
    
     21         102 LOAD_CONST              10 ('account_uri')
    
-    22         104 LOAD_NAME               16 (str)
+    22         104 LOAD_NAME               17 (str)
    
     21         106 LOAD_CONST              11 ('application_name')
    
-    22         108 LOAD_NAME               16 (str)
+    22         108 LOAD_NAME               17 (str)
    
     21         110 LOAD_CONST              12 ('session')
    
     22         112 LOAD_NAME                0 (aiohttp)
-               114 LOAD_ATTR               17 (ClientSession)
+               114 LOAD_ATTR               18 (ClientSession)
    
     21         124 LOAD_CONST              13 ('return')
    
-    23         126 LOAD_NAME                8 (ApplicationAdapterForActor)
+    23         126 LOAD_NAME                7 (ApplicationAdapterForActor)
    
     21         128 BUILD_TUPLE              8
                130 LOAD_CONST              14 (<code object actor_for_application, file "/woodpecker/src/codeberg.org/funfedidev/python_fediverse_pasture/fediverse_pasture/runner/application/__init__.py", line 21>)
                132 MAKE_FUNCTION            4 (annotations)
-               134 STORE_NAME              18 (actor_for_application)
+               134 STORE_NAME              19 (actor_for_application)
    
     50         136 NOP
    
     51         138 NOP
    
     45         140 LOAD_CONST              26 (('mastodon', False))
                142 LOAD_CONST              17 ('domain')
    
-    46         144 LOAD_NAME               16 (str)
+    46         144 LOAD_NAME               17 (str)
    
     45         146 LOAD_CONST              18 ('username')
    
-    47         148 LOAD_NAME               16 (str)
+    47         148 LOAD_NAME               17 (str)
    
     45         150 LOAD_CONST              19 ('access_token')
    
-    48         152 LOAD_NAME               16 (str)
+    48         152 LOAD_NAME               17 (str)
    
     45         154 LOAD_CONST              12 ('session')
    
     49         156 LOAD_NAME                0 (aiohttp)
-               158 LOAD_ATTR               17 (ClientSession)
+               158 LOAD_ATTR               18 (ClientSession)
    
     45         168 LOAD_CONST              11 ('application_name')
    
-    50         170 LOAD_NAME               16 (str)
+    50         170 LOAD_NAME               17 (str)
    
     45         172 LOAD_CONST              20 ('determine_actor_uri')
    
-    51         174 LOAD_NAME               19 (bool)
+    51         174 LOAD_NAME               20 (bool)
    
     45         176 LOAD_CONST              13 ('return')
    
-    52         178 LOAD_NAME                9 (ApplicationAdapterForLastActivity)
+    52         178 LOAD_NAME                8 (ApplicationAdapterForLastActivity)
    
     45         180 BUILD_TUPLE             14
                182 LOAD_CONST              21 (<code object activity_for_mastodon, file "/woodpecker/src/codeberg.org/funfedidev/python_fediverse_pasture/fediverse_pasture/runner/application/__init__.py", line 45>)
                184 MAKE_FUNCTION            5 (defaults, annotations)
-               186 STORE_NAME              20 (activity_for_mastodon)
+               186 STORE_NAME              21 (activity_for_mastodon)
    
     75         188 LOAD_CONST              17 ('domain')
    
-    76         190 LOAD_NAME               16 (str)
+    76         190 LOAD_NAME               17 (str)
    
     75         192 LOAD_CONST              18 ('username')
    
-    76         194 LOAD_NAME               16 (str)
+    76         194 LOAD_NAME               17 (str)
    
     75         196 LOAD_CONST              12 ('session')
    
     76         198 LOAD_NAME                0 (aiohttp)
-               200 LOAD_ATTR               17 (ClientSession)
+               200 LOAD_ATTR               18 (ClientSession)
    
     75         210 LOAD_CONST              13 ('return')
    
-    77         212 LOAD_NAME                9 (ApplicationAdapterForLastActivity)
+    77         212 LOAD_NAME                8 (ApplicationAdapterForLastActivity)
    
     75         214 BUILD_TUPLE              8
                216 LOAD_CONST              22 (<code object activity_for_firefish, file "/woodpecker/src/codeberg.org/funfedidev/python_fediverse_pasture/fediverse_pasture/runner/application/__init__.py", line 75>)
                218 MAKE_FUNCTION            4 (annotations)
-               220 STORE_NAME              21 (activity_for_firefish)
+               220 STORE_NAME              22 (activity_for_firefish)
    
     94         222 NOP
    
     95         224 NOP
    
     90         226 LOAD_CONST              26 (('mastodon', False))
                228 LOAD_CONST              17 ('domain')
    
-    91         230 LOAD_NAME               16 (str)
+    91         230 LOAD_NAME               17 (str)
    
     90         232 LOAD_CONST              18 ('username')
    
-    92         234 LOAD_NAME               16 (str)
+    92         234 LOAD_NAME               17 (str)
    
     90         236 LOAD_CONST              19 ('access_token')
    
-    93         238 LOAD_NAME               16 (str)
+    93         238 LOAD_NAME               17 (str)
    
     90         240 LOAD_CONST              11 ('application_name')
    
-    94         242 LOAD_NAME               16 (str)
+    94         242 LOAD_NAME               17 (str)
    
     90         244 LOAD_CONST              20 ('determine_actor_uri')
    
-    95         246 LOAD_NAME               19 (bool)
+    95         246 LOAD_NAME               20 (bool)
    
     90         248 LOAD_CONST              13 ('return')
    
-    96         250 LOAD_NAME                3 (Callable)
+    96         250 LOAD_NAME                2 (Callable)
                252 LOAD_NAME                0 (aiohttp)
-               254 LOAD_ATTR               17 (ClientSession)
+               254 LOAD_ATTR               18 (ClientSession)
                264 BUILD_LIST               1
-               266 LOAD_NAME                4 (Awaitable)
-               268 LOAD_NAME                9 (ApplicationAdapterForLastActivity)
+               266 LOAD_NAME                3 (Awaitable)
+               268 LOAD_NAME                8 (ApplicationAdapterForLastActivity)
                270 BINARY_SUBSCR
                280 BUILD_TUPLE              2
                282 BINARY_SUBSCR
    
     90         292 BUILD_TUPLE             12
                294 LOAD_CONST              23 (<code object activity_for_mastodon_provider, file "/woodpecker/src/codeberg.org/funfedidev/python_fediverse_pasture/fediverse_pasture/runner/application/__init__.py", line 90>)
                296 MAKE_FUNCTION            5 (defaults, annotations)
-               298 STORE_NAME              22 (activity_for_mastodon_provider)
+               298 STORE_NAME              23 (activity_for_mastodon_provider)
    
    110         300 LOAD_CONST              17 ('domain')
    
-   111         302 LOAD_NAME               16 (str)
+   111         302 LOAD_NAME               17 (str)
    
    110         304 LOAD_CONST              18 ('username')
    
-   112         306 LOAD_NAME               16 (str)
+   112         306 LOAD_NAME               17 (str)
    
    110         308 LOAD_CONST              13 ('return')
    
-   113         310 LOAD_NAME                3 (Callable)
+   113         310 LOAD_NAME                2 (Callable)
                312 LOAD_NAME                0 (aiohttp)
-               314 LOAD_ATTR               17 (ClientSession)
+               314 LOAD_ATTR               18 (ClientSession)
                324 BUILD_LIST               1
-               326 LOAD_NAME                4 (Awaitable)
-               328 LOAD_NAME                9 (ApplicationAdapterForLastActivity)
+               326 LOAD_NAME                3 (Awaitable)
+               328 LOAD_NAME                8 (ApplicationAdapterForLastActivity)
                330 BINARY_SUBSCR
                340 BUILD_TUPLE              2
                342 BINARY_SUBSCR
    
    110         352 BUILD_TUPLE              6
                354 LOAD_CONST              24 (<code object activity_for_misskey_provider, file "/woodpecker/src/codeberg.org/funfedidev/python_fediverse_pasture/fediverse_pasture/runner/application/__init__.py", line 110>)
                356 MAKE_FUNCTION            4 (annotations)
-               358 STORE_NAME              23 (activity_for_misskey_provider)
+               358 STORE_NAME              24 (activity_for_misskey_provider)
    
-   157         360 LOAD_CONST              25 (<code object activity_for_bovine_provider, file "/woodpecker/src/codeberg.org/funfedidev/python_fediverse_pasture/fediverse_pasture/runner/application/__init__.py", line 157>)
+   126         360 LOAD_CONST              25 (<code object activity_for_bovine_provider, file "/woodpecker/src/codeberg.org/funfedidev/python_fediverse_pasture/fediverse_pasture/runner/application/__init__.py", line 126>)
                362 MAKE_FUNCTION            0
-               364 STORE_NAME              24 (activity_for_bovine_provider)
+               364 STORE_NAME              25 (activity_for_bovine_provider)
                366 LOAD_CONST               1 (None)
                368 RETURN_VALUE
    consts
       0
       None
-      ('datetime',)
       ('Callable', 'Awaitable')
       ('lookup_uri_with_webfinger',)
       ('ApplicationAdapterForActor', 'ApplicationAdapterForLastActivity')
       1
       ('MastodonApplication',)
+      ('MisskeyApplication',)
       ('FirefishApplication',)
       ('BovineApplication',)
       'account_uri'
       'application_name'
       'session'
       'return'
       code
@@ -570,15 +570,15 @@
                       32 LOAD_CLOSURE             0 (domain)
                       34 LOAD_CLOSURE             1 (username)
                       36 BUILD_TUPLE              2
                       38 LOAD_CONST               2 (<code object func, file "/woodpecker/src/codeberg.org/funfedidev/python_fediverse_pasture/fediverse_pasture/runner/application/__init__.py", line 115>)
                       40 MAKE_FUNCTION           12 (annotations, closure)
                       42 STORE_FAST               2 (func)
          
-         154          44 LOAD_FAST                2 (func)
+         123          44 LOAD_FAST                2 (func)
                       46 RETURN_VALUE
          consts
             None
             'session'
             code
                argcount  : 1
                nlocals   : 2
@@ -596,408 +596,159 @@
                              8 LOAD_CLOSURE             0 (session)
                             10 LOAD_CLOSURE             3 (username)
                             12 BUILD_TUPLE              3
                             14 LOAD_CONST               1 (<code object misskey, file "/woodpecker/src/codeberg.org/funfedidev/python_fediverse_pasture/fediverse_pasture/runner/application/__init__.py", line 116>)
                             16 MAKE_FUNCTION            8 (closure)
                             18 STORE_FAST               1 (misskey)
                
-               152          20 PUSH_NULL
+               121          20 PUSH_NULL
                             22 LOAD_FAST                1 (misskey)
                             24 PRECALL                  0
                             28 CALL                     0
                             38 RETURN_VALUE
                consts
                   None
                   code
                      argcount  : 0
-                     nlocals   : 2
+                     nlocals   : 1
                      stacksize : 5
                      flags     : 147
                      code
-                        0x950387024b0001009700740100000000000000000000890389058904a6
-                        030000ab030000000000000000830064007b035600970386047d0089037c
-                        005f01000000000000000088046601640184088a02640274040000000000
-                        000000000066028802880466026403840c7d017c017c005f030000000000
-                        0000007c005300
+                        0x95034b0001009700740100000000000000000000890189038902ac01a6
+                        030000ab0300000000000000007d007c00a0010000000000000000000000
+                        000000000000000000a6000000ab000000000000000000830064007b0356
+                        00970386045300
                                    0 COPY_FREE_VARS           3
-                                   2 MAKE_CELL                2 (determine_actor_misskey_id)
                      
-                     116           4 RETURN_GENERATOR
-                                   6 POP_TOP
-                                   8 RESUME                   0
+                     116           2 RETURN_GENERATOR
+                                   4 POP_TOP
+                                   6 RESUME                   0
                      
-                     117          10 LOAD_GLOBAL              1 (NULL + activity_for_firefish)
-                                  22 LOAD_DEREF               3 (domain)
-                                  24 LOAD_DEREF               5 (username)
-                                  26 LOAD_DEREF               4 (session)
+                     117           8 LOAD_GLOBAL              1 (NULL + MisskeyApplication)
+                                  20 LOAD_DEREF               1 (domain)
+                                  22 LOAD_DEREF               3 (username)
+                                  24 LOAD_DEREF               2 (session)
+                                  26 KW_NAMES                 1
                                   28 PRECALL                  3
                                   32 CALL                     3
-                                  42 GET_AWAITABLE            0
-                                  44 LOAD_CONST               0 (None)
-                             >>   46 SEND                     3 (to 54)
-                                  48 YIELD_VALUE
-                                  50 RESUME                   3
-                                  52 JUMP_BACKWARD_NO_INTERRUPT     4 (to 46)
-                             >>   54 STORE_FAST               0 (app)
+                                  42 STORE_FAST               0 (app)
                      
-                     118          56 LOAD_DEREF               3 (domain)
-                                  58 LOAD_FAST                0 (app)
-                                  60 STORE_ATTR               1 (application_name)
-                     
-                     120          70 LOAD_CLOSURE             4 (session)
-                                  72 BUILD_TUPLE              1
-                                  74 LOAD_CONST               1 (<code object determine_actor_misskey_id, file "/woodpecker/src/codeberg.org/funfedidev/python_fediverse_pasture/fediverse_pasture/runner/application/__init__.py", line 120>)
-                                  76 MAKE_FUNCTION            8 (closure)
-                                  78 STORE_DEREF              2 (determine_actor_misskey_id)
-                     
-                     132          80 LOAD_CONST               2 ('published')
-                                  82 LOAD_GLOBAL              4 (datetime)
-                                  94 BUILD_TUPLE              2
-                                  96 LOAD_CLOSURE             2 (determine_actor_misskey_id)
-                                  98 LOAD_CLOSURE             4 (session)
-                                 100 BUILD_TUPLE              2
-                                 102 LOAD_CONST               3 (<code object user_post_with_published, file "/woodpecker/src/codeberg.org/funfedidev/python_fediverse_pasture/fediverse_pasture/runner/application/__init__.py", line 132>)
-                                 104 MAKE_FUNCTION           12 (annotations, closure)
-                                 106 STORE_FAST               1 (user_post_with_published)
-                     
-                     148         108 LOAD_FAST                1 (user_post_with_published)
-                                 110 LOAD_FAST                0 (app)
-                                 112 STORE_ATTR               3 (fetch_activity)
-                     
-                     150         122 LOAD_FAST                0 (app)
-                                 124 RETURN_VALUE
+                     119          44 LOAD_FAST                0 (app)
+                                  46 LOAD_METHOD              1 (last_activity)
+                                  68 PRECALL                  0
+                                  72 CALL                     0
+                                  82 GET_AWAITABLE            0
+                                  84 LOAD_CONST               0 (None)
+                             >>   86 SEND                     3 (to 94)
+                                  88 YIELD_VALUE
+                                  90 RESUME                   3
+                                  92 JUMP_BACKWARD_NO_INTERRUPT     4 (to 86)
+                             >>   94 RETURN_VALUE
                      consts
                         None
-                        code
-                           argcount  : 0
-                           nlocals   : 3
-                           stacksize : 6
-                           flags     : 147
-                           code
-                              0x95014b00010097008903a0000000000000000000000000000000000000
-                              0000006401640264036901640464056901ac06a6030000ab030000000000
-                              000000830064007b035600970386047d007c00a001000000000000000000
-                              0000000000000000000000a6000000ab000000000000000000830064007b
-                              035600970386047d017c0144005d327d027c02a002000000000000000000
-                              00000000000000000000006407a6010000ab01000000000000000064086b
-                              020000000072177c02a00200000000000000000000000000000000000000
-                              006409a6010000ab0100000000000000006302010053008c3364005300
-                                         0 COPY_FREE_VARS           1
-                           
-                           120           2 RETURN_GENERATOR
-                                         4 POP_TOP
-                                         6 RESUME                   0
-                           
-                           121           8 LOAD_DEREF               3 (session)
-                                        10 LOAD_METHOD              0 (post)
-                           
-                           122          32 LOAD_CONST               1 ('http://misskey/api/users/search')
-                           
-                           123          34 LOAD_CONST               2 ('query')
-                                        36 LOAD_CONST               3 ('actor')
-                                        38 BUILD_MAP                1
-                           
-                           124          40 LOAD_CONST               4 ('content-type')
-                                        42 LOAD_CONST               5 ('application/json')
-                                        44 BUILD_MAP                1
-                           
-                           121          46 KW_NAMES                 6
-                                        48 PRECALL                  3
-                                        52 CALL                     3
-                                        62 GET_AWAITABLE            0
-                                        64 LOAD_CONST               0 (None)
-                                   >>   66 SEND                     3 (to 74)
-                                        68 YIELD_VALUE
-                                        70 RESUME                   3
-                                        72 JUMP_BACKWARD_NO_INTERRUPT     4 (to 66)
-                                   >>   74 STORE_FAST               0 (response)
-                           
-                           126          76 LOAD_FAST                0 (response)
-                                        78 LOAD_METHOD              1 (json)
-                                       100 PRECALL                  0
-                                       104 CALL                     0
-                                       114 GET_AWAITABLE            0
-                                       116 LOAD_CONST               0 (None)
-                                   >>  118 SEND                     3 (to 126)
-                                       120 YIELD_VALUE
-                                       122 RESUME                   3
-                                       124 JUMP_BACKWARD_NO_INTERRUPT     4 (to 118)
-                                   >>  126 STORE_FAST               1 (users)
-                           
-                           128         128 LOAD_FAST                1 (users)
-                                       130 GET_ITER
-                                   >>  132 FOR_ITER                50 (to 234)
-                                       134 STORE_FAST               2 (user)
-                           
-                           129         136 LOAD_FAST                2 (user)
-                                       138 LOAD_METHOD              2 (get)
-                                       160 LOAD_CONST               7 ('host')
-                                       162 PRECALL                  1
-                                       166 CALL                     1
-                                       176 LOAD_CONST               8 ('pasture-one-actor')
-                                       178 COMPARE_OP               2 (==)
-                                       184 POP_JUMP_FORWARD_IF_FALSE    23 (to 232)
-                           
-                           130         186 LOAD_FAST                2 (user)
-                                       188 LOAD_METHOD              2 (get)
-                                       210 LOAD_CONST               9 ('id')
-                                       212 PRECALL                  1
-                                       216 CALL                     1
-                                       226 SWAP                     2
-                                       228 POP_TOP
-                                       230 RETURN_VALUE
-                           
-                           129     >>  232 JUMP_BACKWARD           51 (to 132)
-                           
-                           128     >>  234 LOAD_CONST               0 (None)
-                                       236 RETURN_VALUE
-                           consts
-                              None
-                              'http://misskey/api/users/search'
-                              'query'
-                              'actor'
-                              'content-type'
-                              'application/json'
-                              ('json', 'headers')
-                              'host'
-                              'pasture-one-actor'
-                              'id'
-                           names      ('post', 'json', 'get')
-                           varnames   ('response', 'users', 'user')
-                           freevars   ('session',)
-                           cellvars   ()
-                           filename   '/woodpecker/src/codeberg.org/funfedidev/python_fediverse_pasture/fediverse_pasture/runner/application/__init__.py'
-                           name       'determine_actor_misskey_id'
-                           firstlineno 120
-                           lnotab 0x080118010201060106fd1e053402080132012eff02ff
-                        'published'
-                        code
-                           argcount  : 1
-                           nlocals   : 6
-                           stacksize : 6
-                           flags     : 147
-                           code
-                              0x95024b000100970002008906a6000000ab000000000000000000830064
-                              007b035600970386047d018907a000000000000000000000000000000000
-                              0000000000640164027c016901640364046901ac05a6030000ab03000000
-                              0000000000830064007b035600970386047d027c02a00100000000000000
-                              00000000000000000000000000a6000000ab000000000000000000830064
-                              007b035600970386047d037c0344005d487d047c04a00200000000000000
-                              000000000000000000000000006406a6010000ab0100000000000000007d
-                              057407000000000000000000006a0400000000000000007c05a005000000
-                              00000000000000000000000000000000006407a6010000ab010000000000
-                              000000a6010000ab0100000000000000007d057c057c006b020000000072
-                              047c046302010053008c4964005300
-                                         0 COPY_FREE_VARS           2
-                           
-                           132           2 RETURN_GENERATOR
-                                         4 POP_TOP
-                                         6 RESUME                   0
-                           
-                           133           8 PUSH_NULL
-                                        10 LOAD_DEREF               6 (determine_actor_misskey_id)
-                                        12 PRECALL                  0
-                                        16 CALL                     0
-                                        26 GET_AWAITABLE            0
-                                        28 LOAD_CONST               0 (None)
-                                   >>   30 SEND                     3 (to 38)
-                                        32 YIELD_VALUE
-                                        34 RESUME                   3
-                                        36 JUMP_BACKWARD_NO_INTERRUPT     4 (to 30)
-                                   >>   38 STORE_FAST               1 (misskey_id)
-                           
-                           135          40 LOAD_DEREF               7 (session)
-                                        42 LOAD_METHOD              0 (post)
-                           
-                           136          64 LOAD_CONST               1 ('http://misskey/api/users/notes')
-                           
-                           137          66 LOAD_CONST               2 ('userId')
-                                        68 LOAD_FAST                1 (misskey_id)
-                                        70 BUILD_MAP                1
-                           
-                           138          72 LOAD_CONST               3 ('Authorization')
-                                        74 LOAD_CONST               4 ('Bearer token')
-                                        76 BUILD_MAP                1
-                           
-                           135          78 KW_NAMES                 5
-                                        80 PRECALL                  3
-                                        84 CALL                     3
-                                        94 GET_AWAITABLE            0
-                                        96 LOAD_CONST               0 (None)
-                                   >>   98 SEND                     3 (to 106)
-                                       100 YIELD_VALUE
-                                       102 RESUME                   3
-                                       104 JUMP_BACKWARD_NO_INTERRUPT     4 (to 98)
-                                   >>  106 STORE_FAST               2 (response)
-                           
-                           140         108 LOAD_FAST                2 (response)
-                                       110 LOAD_METHOD              1 (json)
-                                       132 PRECALL                  0
-                                       136 CALL                     0
-                                       146 GET_AWAITABLE            0
-                                       148 LOAD_CONST               0 (None)
-                                   >>  150 SEND                     3 (to 158)
-                                       152 YIELD_VALUE
-                                       154 RESUME                   3
-                                       156 JUMP_BACKWARD_NO_INTERRUPT     4 (to 150)
-                                   >>  158 STORE_FAST               3 (notes)
-                           
-                           142         160 LOAD_FAST                3 (notes)
-                                       162 GET_ITER
-                                   >>  164 FOR_ITER                72 (to 310)
-                                       166 STORE_FAST               4 (data)
-                           
-                           143         168 LOAD_FAST                4 (data)
-                                       170 LOAD_METHOD              2 (get)
-                                       192 LOAD_CONST               6 ('createdAt')
-                                       194 PRECALL                  1
-                                       198 CALL                     1
-                                       208 STORE_FAST               5 (created_at)
-                           
-                           144         210 LOAD_GLOBAL              7 (NULL + datetime)
-                                       222 LOAD_ATTR                4 (fromisoformat)
-                                       232 LOAD_FAST                5 (created_at)
-                                       234 LOAD_METHOD              5 (removesuffix)
-                                       256 LOAD_CONST               7 ('Z')
-                                       258 PRECALL                  1
-                                       262 CALL                     1
-                                       272 PRECALL                  1
-                                       276 CALL                     1
-                                       286 STORE_FAST               5 (created_at)
-                           
-                           145         288 LOAD_FAST                5 (created_at)
-                                       290 LOAD_FAST                0 (published)
-                                       292 COMPARE_OP               2 (==)
-                                       298 POP_JUMP_FORWARD_IF_FALSE     4 (to 308)
-                           
-                           146         300 LOAD_FAST                4 (data)
-                                       302 SWAP                     2
-                                       304 POP_TOP
-                                       306 RETURN_VALUE
-                           
-                           145     >>  308 JUMP_BACKWARD           73 (to 164)
-                           
-                           142     >>  310 LOAD_CONST               0 (None)
-                                       312 RETURN_VALUE
-                           consts
-                              None
-                              'http://misskey/api/users/notes'
-                              'userId'
-                              'Authorization'
-                              'Bearer token'
-                              ('json', 'headers')
-                              'createdAt'
-                              'Z'
-                           names      ('post', 'json', 'get', 'datetime', 'fromisoformat', 'removesuffix')
-                           varnames   ('published', 'misskey_id', 'response', 'notes', 'data', 'created_at')
-                           freevars   ('determine_actor_misskey_id', 'session')
-                           cellvars   ()
-                           filename   '/woodpecker/src/codeberg.org/funfedidev/python_fediverse_pasture/fediverse_pasture/runner/application/__init__.py'
-                           name       'user_post_with_published'
-                           firstlineno 132
-                           lnotab 0x0801200218010201060106fd1e05340208012a014e010c0108ff02fd
-                     names      ('activity_for_firefish', 'application_name', 'datetime', 'fetch_activity')
-                     varnames   ('app', 'user_post_with_published')
+                        ('session',)
+                     names      ('MisskeyApplication', 'last_activity')
+                     varnames   ('app',)
                      freevars   ('domain', 'session', 'username')
-                     cellvars   ('determine_actor_misskey_id',)
+                     cellvars   ()
                      filename   '/woodpecker/src/codeberg.org/funfedidev/python_fediverse_pasture/fediverse_pasture/runner/application/__init__.py'
                      name       'misskey'
                      firstlineno 116
-                     lnotab 0x0a012e010e020a0c1c100e02
+                     lnotab 0x08012402
                names      ()
                varnames   ('session', 'misskey')
                freevars   ('domain', 'username')
                cellvars   ('session',)
                filename   '/woodpecker/src/codeberg.org/funfedidev/python_fediverse_pasture/fediverse_pasture/runner/application/__init__.py'
                name       'func'
                firstlineno 115
-               lnotab 0x06010e24
+               lnotab 0x06010e05
          names      ('aiohttp', 'ClientSession')
          varnames   ('domain', 'username', 'func')
          freevars   ()
          cellvars   ('domain', 'username')
          filename   '/woodpecker/src/codeberg.org/funfedidev/python_fediverse_pasture/fediverse_pasture/runner/application/__init__.py'
          name       'activity_for_misskey_provider'
          firstlineno 110
-         lnotab 0x06052627
+         lnotab 0x06052608
       code
          argcount  : 3
          nlocals   : 4
          stacksize : 5
          flags     : 3
          code
             0x870497007401000000000000000000007c007c017c02ac01a6030000ab
             0300000000000000008a0488046601640284087d037c035300
                        0 MAKE_CELL                4 (app)
          
-         157           2 RESUME                   0
+         126           2 RESUME                   0
          
-         158           4 LOAD_GLOBAL              1 (NULL + BovineApplication)
+         127           4 LOAD_GLOBAL              1 (NULL + BovineApplication)
                       16 LOAD_FAST                0 (domain)
                       18 LOAD_FAST                1 (username)
                       20 LOAD_FAST                2 (secret)
                       22 KW_NAMES                 1
                       24 PRECALL                  3
                       28 CALL                     3
                       38 STORE_DEREF              4 (app)
          
-         160          40 LOAD_CLOSURE             4 (app)
+         129          40 LOAD_CLOSURE             4 (app)
                       42 BUILD_TUPLE              1
-                      44 LOAD_CONST               2 (<code object func, file "/woodpecker/src/codeberg.org/funfedidev/python_fediverse_pasture/fediverse_pasture/runner/application/__init__.py", line 160>)
+                      44 LOAD_CONST               2 (<code object func, file "/woodpecker/src/codeberg.org/funfedidev/python_fediverse_pasture/fediverse_pasture/runner/application/__init__.py", line 129>)
                       46 MAKE_FUNCTION            8 (closure)
                       48 STORE_FAST               3 (func)
          
-         163          50 LOAD_FAST                3 (func)
+         132          50 LOAD_FAST                3 (func)
                       52 RETURN_VALUE
          consts
             None
             ('domain', 'username', 'secret')
             code
                argcount  : 1
                nlocals   : 1
                stacksize : 3
                flags     : 19
                code
                   0x950197008901a00000000000000000000000000000000000000000007c
                   00a6010000ab0100000000000000005300
                              0 COPY_FREE_VARS           1
                
-               160           2 RESUME                   0
+               129           2 RESUME                   0
                
-               161           4 LOAD_DEREF               1 (app)
+               130           4 LOAD_DEREF               1 (app)
                              6 LOAD_METHOD              0 (last_activity)
                             28 LOAD_FAST                0 (session)
                             30 PRECALL                  1
                             34 CALL                     1
                             44 RETURN_VALUE
                consts
                   None
                names      ('last_activity',)
                varnames   ('session',)
                freevars   ('app',)
                cellvars   ()
                filename   '/woodpecker/src/codeberg.org/funfedidev/python_fediverse_pasture/fediverse_pasture/runner/application/__init__.py'
                name       'func'
-               firstlineno 160
+               firstlineno 129
                lnotab 0x0401
          names      ('BovineApplication',)
          varnames   ('domain', 'username', 'secret', 'func')
          freevars   ()
          cellvars   ('app',)
          filename   '/woodpecker/src/codeberg.org/funfedidev/python_fediverse_pasture/fediverse_pasture/runner/application/__init__.py'
          name       'activity_for_bovine_provider'
-         firstlineno 157
+         firstlineno 126
          lnotab 0x040124020a03
       ('mastodon', False)
-   names      ('aiohttp', 'datetime', 'typing', 'Callable', 'Awaitable', 'bovine.clients', 'lookup_uri_with_webfinger', 'fediverse_pasture.types', 'ApplicationAdapterForActor', 'ApplicationAdapterForLastActivity', 'mastodon', 'MastodonApplication', 'firefish', 'FirefishApplication', 'bovine', 'BovineApplication', 'str', 'ClientSession', 'actor_for_application', 'bool', 'activity_for_mastodon', 'activity_for_firefish', 'activity_for_mastodon_provider', 'activity_for_misskey_provider', 'activity_for_bovine_provider')
+   names      ('aiohttp', 'typing', 'Callable', 'Awaitable', 'bovine.clients', 'lookup_uri_with_webfinger', 'fediverse_pasture.types', 'ApplicationAdapterForActor', 'ApplicationAdapterForLastActivity', 'mastodon', 'MastodonApplication', 'misskey', 'MisskeyApplication', 'firefish', 'FirefishApplication', 'bovine', 'BovineApplication', 'str', 'ClientSession', 'actor_for_application', 'bool', 'activity_for_mastodon', 'activity_for_firefish', 'activity_for_mastodon_provider', 'activity_for_misskey_provider', 'activity_for_bovine_provider')
    varnames   ()
    freevars   ()
    cellvars   ()
    filename   '/woodpecker/src/codeberg.org/funfedidev/python_fediverse_pasture/fediverse_pasture/runner/application/__init__.py'
    name       '<module>'
    firstlineno 1
    lnotab
-      0x00ff020508010c0110010c0210060c010c010c03020102ff020102ff02
+      0x00ff0205080110010c0210060c010c010c010c03020102ff020102ff02
       010cff020202fe081d020102fa040102ff020202fe020302fd02040cfc02
       0502fb020602fa020702f9081e020102ff020102ff02010cff020202fe08
       13020102fb040102ff020202fe020302fd020402fc020502fb02062afa08
-      14020102ff020202fe02032afd082f
+      14020102ff020202fe02032afd0810
```

### Comparing `fediverse_pasture-0.2.8/fediverse_pasture/runner/application/__pycache__/bovine.cpython-311.pyc` & `fediverse_pasture-0.2.9/fediverse_pasture/runner/application/__pycache__/bovine.cpython-311.pyc`

 * *Files 1% similar despite different names*

#### Python bytecode

```diff
@@ -1,9 +1,9 @@
 magic:    0xa70d0d0a
-moddate:  0xf44def65 (Mon Mar 11 18:31:16 2024 UTC)
+moddate:  0xa6340966 (Sun Mar 31 10:02:14 2024 UTC)
 files sz: 1434
 code
    argcount  : 0
    nlocals   : 0
    stacksize : 5
    flags     : 0
    code
```

### Comparing `fediverse_pasture-0.2.8/fediverse_pasture/runner/application/__pycache__/firefish.cpython-311.pyc` & `fediverse_pasture-0.2.9/fediverse_pasture/runner/application/__pycache__/firefish.cpython-311.pyc`

 * *Files 0% similar despite different names*

#### Python bytecode

```diff
@@ -1,9 +1,9 @@
 magic:    0xa70d0d0a
-moddate:  0xf44def65 (Mon Mar 11 18:31:16 2024 UTC)
+moddate:  0xa6340966 (Sun Mar 31 10:02:14 2024 UTC)
 files sz: 2887
 code
    argcount  : 0
    nlocals   : 0
    stacksize : 5
    flags     : 0
    code
```

### Comparing `fediverse_pasture-0.2.8/fediverse_pasture/runner/application/__pycache__/mastodon.cpython-311.pyc` & `fediverse_pasture-0.2.9/fediverse_pasture/runner/application/__pycache__/mastodon.cpython-311.pyc`

 * *Files 20% similar despite different names*

#### Python bytecode

```diff
@@ -1,189 +1,180 @@
 magic:    0xa70d0d0a
-moddate:  0xf44def65 (Mon Mar 11 18:31:16 2024 UTC)
-files sz: 1810
+moddate:  0xa6340966 (Sun Mar 31 10:02:14 2024 UTC)
+files sz: 1584
 code
    argcount  : 0
    nlocals   : 0
    stacksize : 5
    flags     : 0
    code
-      0x9700640064016c006d015a010100640064026c026d025a020100640064
-      036c035a03640064036c045a04640064036c055a05640064046c066d075a
-      070100640064056c086d095a090100020065036a0a000000000000000065
-      0ba6010000ab0100000000000000005a0c650102004700640684006407a6
-      020000ab020000000000000000a6000000ab0000000000000000005a0d64
-      035300
+      0x9700640064016c006d015a010100640064026c025a02640064026c035a
+      03640064026c045a04640064036c056d065a060100640064046c076d085a
+      080100020065026a090000000000000000650aa6010000ab010000000000
+      0000005a0b650102004700640584006406a6020000ab0200000000000000
+      00a6000000ab0000000000000000005a0c64025300
      0           0 RESUME                   0
    
      5           2 LOAD_CONST               0 (0)
                  4 LOAD_CONST               1 (('dataclass',))
                  6 IMPORT_NAME              0 (dataclasses)
                  8 IMPORT_FROM              1 (dataclass)
                 10 STORE_NAME               1 (dataclass)
                 12 POP_TOP
    
      6          14 LOAD_CONST               0 (0)
-                16 LOAD_CONST               2 (('datetime',))
-                18 IMPORT_NAME              2 (datetime)
-                20 IMPORT_FROM              2 (datetime)
-                22 STORE_NAME               2 (datetime)
-                24 POP_TOP
-   
-     7          26 LOAD_CONST               0 (0)
-                28 LOAD_CONST               3 (None)
-                30 IMPORT_NAME              3 (logging)
-                32 STORE_NAME               3 (logging)
-   
-     8          34 LOAD_CONST               0 (0)
-                36 LOAD_CONST               3 (None)
-                38 IMPORT_NAME              4 (json)
-                40 STORE_NAME               4 (json)
-   
-     9          42 LOAD_CONST               0 (0)
-                44 LOAD_CONST               3 (None)
-                46 IMPORT_NAME              5 (aiohttp)
-                48 STORE_NAME               5 (aiohttp)
-   
-    11          50 LOAD_CONST               0 (0)
-                52 LOAD_CONST               4 (('BearerAuthClient',))
-                54 IMPORT_NAME              6 (bovine.clients.bearer)
-                56 IMPORT_FROM              7 (BearerAuthClient)
-                58 STORE_NAME               7 (BearerAuthClient)
+                16 LOAD_CONST               2 (None)
+                18 IMPORT_NAME              2 (logging)
+                20 STORE_NAME               2 (logging)
+   
+     7          22 LOAD_CONST               0 (0)
+                24 LOAD_CONST               2 (None)
+                26 IMPORT_NAME              3 (json)
+                28 STORE_NAME               3 (json)
+   
+     8          30 LOAD_CONST               0 (0)
+                32 LOAD_CONST               2 (None)
+                34 IMPORT_NAME              4 (aiohttp)
+                36 STORE_NAME               4 (aiohttp)
+   
+    10          38 LOAD_CONST               0 (0)
+                40 LOAD_CONST               3 (('BearerAuthClient',))
+                42 IMPORT_NAME              5 (bovine.clients.bearer)
+                44 IMPORT_FROM              6 (BearerAuthClient)
+                46 STORE_NAME               6 (BearerAuthClient)
+                48 POP_TOP
+   
+    12          50 LOAD_CONST               0 (0)
+                52 LOAD_CONST               4 (('ApplicationAdapterForLastActivity',))
+                54 IMPORT_NAME              7 (fediverse_pasture.types)
+                56 IMPORT_FROM              8 (ApplicationAdapterForLastActivity)
+                58 STORE_NAME               8 (ApplicationAdapterForLastActivity)
                 60 POP_TOP
    
-    13          62 LOAD_CONST               0 (0)
-                64 LOAD_CONST               5 (('ApplicationAdapterForLastActivity',))
-                66 IMPORT_NAME              8 (fediverse_pasture.types)
-                68 IMPORT_FROM              9 (ApplicationAdapterForLastActivity)
-                70 STORE_NAME               9 (ApplicationAdapterForLastActivity)
-                72 POP_TOP
-   
-    15          74 PUSH_NULL
-                76 LOAD_NAME                3 (logging)
-                78 LOAD_ATTR               10 (getLogger)
-                88 LOAD_NAME               11 (__name__)
-                90 PRECALL                  1
-                94 CALL                     1
-               104 STORE_NAME              12 (logger)
-   
-    18         106 LOAD_NAME                1 (dataclass)
-   
-    19         108 PUSH_NULL
-               110 LOAD_BUILD_CLASS
-               112 LOAD_CONST               6 (<code object MastodonApplication, file "/woodpecker/src/codeberg.org/funfedidev/python_fediverse_pasture/fediverse_pasture/runner/application/mastodon.py", line 18>)
-               114 MAKE_FUNCTION            0
-               116 LOAD_CONST               7 ('MastodonApplication')
-               118 PRECALL                  2
-               122 CALL                     2
-   
-    18         132 PRECALL                  0
-               136 CALL                     0
-   
-    19         146 STORE_NAME              13 (MastodonApplication)
-               148 LOAD_CONST               3 (None)
-               150 RETURN_VALUE
+    14          62 PUSH_NULL
+                64 LOAD_NAME                2 (logging)
+                66 LOAD_ATTR                9 (getLogger)
+                76 LOAD_NAME               10 (__name__)
+                78 PRECALL                  1
+                82 CALL                     1
+                92 STORE_NAME              11 (logger)
+   
+    17          94 LOAD_NAME                1 (dataclass)
+   
+    18          96 PUSH_NULL
+                98 LOAD_BUILD_CLASS
+               100 LOAD_CONST               5 (<code object MastodonApplication, file "/woodpecker/src/codeberg.org/funfedidev/python_fediverse_pasture/fediverse_pasture/runner/application/mastodon.py", line 17>)
+               102 MAKE_FUNCTION            0
+               104 LOAD_CONST               6 ('MastodonApplication')
+               106 PRECALL                  2
+               110 CALL                     2
+   
+    17         120 PRECALL                  0
+               124 CALL                     0
+   
+    18         134 STORE_NAME              12 (MastodonApplication)
+               136 LOAD_CONST               2 (None)
+               138 RETURN_VALUE
    consts
       0
       ('dataclass',)
-      ('datetime',)
       None
       ('BearerAuthClient',)
       ('ApplicationAdapterForLastActivity',)
       code
          argcount  : 0
          nlocals   : 0
          stacksize : 7
          flags     : 0
          code
             0x970065005a0164005a0255006503650464013c0000006503650464023c
             0000006503650464033c00000064045a05650664047a070000650464053c
             00000064045a07650364047a070000650464063c000000640784005a0864
-            0884005a096409650a640a650b64047a0700006604640b84045a0c090064
-            10640d650d6a0e0000000000000000640e6503640a650f6606640f84055a
-            1064045300
-          18           0 RESUME                   0
+            0884005a0964096503640a650a64047a0700006604640b84045a0b090064
+            10640d650c6a0d0000000000000000640e6503640a650e6606640f84055a
+            0f64045300
+          17           0 RESUME                   0
                        2 LOAD_NAME                0 (__name__)
                        4 STORE_NAME               1 (__module__)
                        6 LOAD_CONST               0 ('MastodonApplication')
                        8 STORE_NAME               2 (__qualname__)
                       10 SETUP_ANNOTATIONS
          
-          20          12 LOAD_NAME                3 (str)
+          19          12 LOAD_NAME                3 (str)
                       14 LOAD_NAME                4 (__annotations__)
                       16 LOAD_CONST               1 ('domain')
                       18 STORE_SUBSCR
          
-          21          22 LOAD_NAME                3 (str)
+          20          22 LOAD_NAME                3 (str)
                       24 LOAD_NAME                4 (__annotations__)
                       26 LOAD_CONST               2 ('access_token')
                       28 STORE_SUBSCR
          
-          22          32 LOAD_NAME                3 (str)
+          21          32 LOAD_NAME                3 (str)
                       34 LOAD_NAME                4 (__annotations__)
                       36 LOAD_CONST               3 ('username')
                       38 STORE_SUBSCR
          
-          23          42 LOAD_CONST               4 (None)
+          22          42 LOAD_CONST               4 (None)
                       44 STORE_NAME               5 (client)
                       46 LOAD_NAME                6 (BearerAuthClient)
                       48 LOAD_CONST               4 (None)
                       50 BINARY_OP                7 (|)
                       54 LOAD_NAME                4 (__annotations__)
                       56 LOAD_CONST               5 ('client')
                       58 STORE_SUBSCR
          
-          24          62 LOAD_CONST               4 (None)
+          23          62 LOAD_CONST               4 (None)
                       64 STORE_NAME               7 (actor_uri)
                       66 LOAD_NAME                3 (str)
                       68 LOAD_CONST               4 (None)
                       70 BINARY_OP                7 (|)
                       74 LOAD_NAME                4 (__annotations__)
                       76 LOAD_CONST               6 ('actor_uri')
                       78 STORE_SUBSCR
          
-          26          82 LOAD_CONST               7 (<code object determine_actor_uri, file "/woodpecker/src/codeberg.org/funfedidev/python_fediverse_pasture/fediverse_pasture/runner/application/mastodon.py", line 26>)
+          25          82 LOAD_CONST               7 (<code object determine_actor_uri, file "/woodpecker/src/codeberg.org/funfedidev/python_fediverse_pasture/fediverse_pasture/runner/application/mastodon.py", line 25>)
                       84 MAKE_FUNCTION            0
                       86 STORE_NAME               8 (determine_actor_uri)
          
-          31          88 LOAD_CONST               8 (<code object top_public, file "/woodpecker/src/codeberg.org/funfedidev/python_fediverse_pasture/fediverse_pasture/runner/application/mastodon.py", line 31>)
+          30          88 LOAD_CONST               8 (<code object public_items, file "/woodpecker/src/codeberg.org/funfedidev/python_fediverse_pasture/fediverse_pasture/runner/application/mastodon.py", line 30>)
                       90 MAKE_FUNCTION            0
-                      92 STORE_NAME               9 (top_public)
+                      92 STORE_NAME               9 (public_items)
          
-          40          94 LOAD_CONST               9 ('published')
-                      96 LOAD_NAME               10 (datetime)
+          39          94 LOAD_CONST               9 ('object_id')
+                      96 LOAD_NAME                3 (str)
                       98 LOAD_CONST              10 ('return')
-                     100 LOAD_NAME               11 (dict)
+                     100 LOAD_NAME               10 (dict)
                      102 LOAD_CONST               4 (None)
                      104 BINARY_OP                7 (|)
                      108 BUILD_TUPLE              4
-                     110 LOAD_CONST              11 (<code object top_public_with_published, file "/woodpecker/src/codeberg.org/funfedidev/python_fediverse_pasture/fediverse_pasture/runner/application/mastodon.py", line 40>)
+                     110 LOAD_CONST              11 (<code object top_public_with_object_id, file "/woodpecker/src/codeberg.org/funfedidev/python_fediverse_pasture/fediverse_pasture/runner/application/mastodon.py", line 39>)
                      112 MAKE_FUNCTION            4 (annotations)
-                     114 STORE_NAME              12 (top_public_with_published)
+                     114 STORE_NAME              11 (top_public_with_object_id)
          
-          52         116 NOP
+          47         116 NOP
          
-          51         118 LOAD_CONST              16 (('mastodon',))
+          46         118 LOAD_CONST              16 (('mastodon',))
                      120 LOAD_CONST              13 ('session')
          
-          52         122 LOAD_NAME               13 (aiohttp)
-                     124 LOAD_ATTR               14 (ClientSession)
+          47         122 LOAD_NAME               12 (aiohttp)
+                     124 LOAD_ATTR               13 (ClientSession)
          
-          51         134 LOAD_CONST              14 ('application_name')
+          46         134 LOAD_CONST              14 ('application_name')
          
-          52         136 LOAD_NAME                3 (str)
+          47         136 LOAD_NAME                3 (str)
          
-          51         138 LOAD_CONST              10 ('return')
+          46         138 LOAD_CONST              10 ('return')
          
-          53         140 LOAD_NAME               15 (ApplicationAdapterForLastActivity)
+          48         140 LOAD_NAME               14 (ApplicationAdapterForLastActivity)
          
-          51         142 BUILD_TUPLE              6
-                     144 LOAD_CONST              15 (<code object last_activity, file "/woodpecker/src/codeberg.org/funfedidev/python_fediverse_pasture/fediverse_pasture/runner/application/mastodon.py", line 51>)
+          46         142 BUILD_TUPLE              6
+                     144 LOAD_CONST              15 (<code object last_activity, file "/woodpecker/src/codeberg.org/funfedidev/python_fediverse_pasture/fediverse_pasture/runner/application/mastodon.py", line 46>)
                      146 MAKE_FUNCTION            5 (defaults, annotations)
-                     148 STORE_NAME              16 (last_activity)
+                     148 STORE_NAME              15 (last_activity)
                      150 LOAD_CONST               4 (None)
                      152 RETURN_VALUE
          consts
             'MastodonApplication'
             'domain'
             'access_token'
             'username'
@@ -195,25 +186,25 @@
                nlocals   : 1
                stacksize : 4
                flags     : 3
                code
                   0x97007c006a00000000000000000072077c006a00000000000000000053
                   0064017c006a0100000000000000009b0064027c006a0200000000000000
                   009b009d045300
-                26           0 RESUME                   0
+                25           0 RESUME                   0
                
-                27           2 LOAD_FAST                0 (self)
+                26           2 LOAD_FAST                0 (self)
                              4 LOAD_ATTR                0 (actor_uri)
                             14 POP_JUMP_FORWARD_IF_FALSE     7 (to 30)
                
-                28          16 LOAD_FAST                0 (self)
+                27          16 LOAD_FAST                0 (self)
                             18 LOAD_ATTR                0 (actor_uri)
                             28 RETURN_VALUE
                
-                29     >>   30 LOAD_CONST               1 ('http://')
+                28     >>   30 LOAD_CONST               1 ('http://')
                             32 LOAD_FAST                0 (self)
                             34 LOAD_ATTR                1 (domain)
                             44 FORMAT_VALUE             0
                             46 LOAD_CONST               2 ('/users/')
                             48 LOAD_FAST                0 (self)
                             50 LOAD_ATTR                2 (username)
                             60 FORMAT_VALUE             0
@@ -225,260 +216,220 @@
                   '/users/'
                names      ('actor_uri', 'domain', 'username')
                varnames   ('self',)
                freevars   ()
                cellvars   ()
                filename   '/woodpecker/src/codeberg.org/funfedidev/python_fediverse_pasture/fediverse_pasture/runner/application/mastodon.py'
                name       'determine_actor_uri'
-               firstlineno 26
+               firstlineno 25
                lnotab 0x02010e010e01
             code
                argcount  : 1
                nlocals   : 3
                stacksize : 6
                flags     : 131
                code
                   0x4b00010097007c006a000000000000000000a001000000000000000000
                   000000000000000000000064017c006a0200000000000000009b0064029d
                   03a6010000ab010000000000000000830064007b035600970386047d017c
                   01a0030000000000000000000000000000000000000000a6000000ab0000
                   00000000000000830064007b035600970386047d02740800000000000000
                   000000a00500000000000000000000000000000000000000007407000000
                   000000000000006a0600000000000000007c026403ac04a6020000ab0200
-                  00000000000000a6010000ab01000000000000000001007c026405190000
-                  000000000000005300
-                31           0 RETURN_GENERATOR
+                  00000000000000a6010000ab01000000000000000001007c025300
+                30           0 RETURN_GENERATOR
                              2 POP_TOP
                              4 RESUME                   0
                
-                32           6 LOAD_FAST                0 (self)
+                31           6 LOAD_FAST                0 (self)
                              8 LOAD_ATTR                0 (client)
                             18 LOAD_METHOD              1 (get)
                
-                33          40 LOAD_CONST               1 ('http://')
+                32          40 LOAD_CONST               1 ('http://')
                             42 LOAD_FAST                0 (self)
                             44 LOAD_ATTR                2 (domain)
                             54 FORMAT_VALUE             0
                             56 LOAD_CONST               2 ('/api/v1/timelines/public')
                             58 BUILD_STRING             3
                
-                32          60 PRECALL                  1
+                31          60 PRECALL                  1
                             64 CALL                     1
                             74 GET_AWAITABLE            0
                             76 LOAD_CONST               0 (None)
                        >>   78 SEND                     3 (to 86)
                             80 YIELD_VALUE
                             82 RESUME                   3
                             84 JUMP_BACKWARD_NO_INTERRUPT     4 (to 78)
                        >>   86 STORE_FAST               1 (response)
                
-                35          88 LOAD_FAST                1 (response)
+                34          88 LOAD_FAST                1 (response)
                             90 LOAD_METHOD              3 (json)
                            112 PRECALL                  0
                            116 CALL                     0
                            126 GET_AWAITABLE            0
                            128 LOAD_CONST               0 (None)
                        >>  130 SEND                     3 (to 138)
                            132 YIELD_VALUE
                            134 RESUME                   3
                            136 JUMP_BACKWARD_NO_INTERRUPT     4 (to 130)
                        >>  138 STORE_FAST               2 (public_timeline)
                
-                36         140 LOAD_GLOBAL              8 (logger)
+                35         140 LOAD_GLOBAL              8 (logger)
                            152 LOAD_METHOD              5 (debug)
                            174 LOAD_GLOBAL              7 (NULL + json)
                            186 LOAD_ATTR                6 (dumps)
                            196 LOAD_FAST                2 (public_timeline)
                            198 LOAD_CONST               3 (2)
                            200 KW_NAMES                 4
                            202 PRECALL                  2
                            206 CALL                     2
                            216 PRECALL                  1
                            220 CALL                     1
                            230 POP_TOP
                
-                38         232 LOAD_FAST                2 (public_timeline)
-                           234 LOAD_CONST               5 (0)
-                           236 BINARY_SUBSCR
-                           246 RETURN_VALUE
+                37         232 LOAD_FAST                2 (public_timeline)
+                           234 RETURN_VALUE
                consts
                   None
                   'http://'
                   '/api/v1/timelines/public'
                   2
                   ('indent',)
-                  0
                names      ('client', 'get', 'domain', 'json', 'logger', 'debug', 'dumps')
                varnames   ('self', 'response', 'public_timeline')
                freevars   ()
                cellvars   ()
                filename   '/woodpecker/src/codeberg.org/funfedidev/python_fediverse_pasture/fediverse_pasture/runner/application/mastodon.py'
-               name       'top_public'
-               firstlineno 31
+               name       'public_items'
+               firstlineno 30
                lnotab 0x0601220114ff1c0334015c02
-            'published'
+            'object_id'
             'return'
             code
                argcount  : 2
-               nlocals   : 4
-               stacksize : 6
+               nlocals   : 3
+               stacksize : 5
                flags     : 131
                code
                   0x4b00010097007c00a00000000000000000000000000000000000000000
-                  00a6000000ab000000000000000000830064007b035600970386047d0274
-                  0200000000000000000000a0020000000000000000000000000000000000
-                  0000007407000000000000000000006a0400000000000000007c026401ac
-                  02a6020000ab020000000000000000a6010000ab01000000000000000001
-                  007c02a00500000000000000000000000000000000000000006403a60100
-                  00ab0100000000000000007d037c03730264005300740d00000000000000
-                  0000006a0700000000000000007c03a00800000000000000000000000000
-                  000000000000006404a6010000ab010000000000000000a6010000ab0100
-                  000000000000007d037c037c016b020000000072027c02530064005300
-                40           0 RETURN_GENERATOR
+                  00a6000000ab000000000000000000830064007b0356009703860444005d
+                  1c7d027c017403000000000000000000006a0200000000000000007c02a6
+                  010000ab010000000000000000760072047c026302010053008c1d640053
+                  00
+                39           0 RETURN_GENERATOR
                              2 POP_TOP
                              4 RESUME                   0
                
-                41           6 LOAD_FAST                0 (self)
-                             8 LOAD_METHOD              0 (top_public)
+                40           6 LOAD_FAST                0 (self)
+                             8 LOAD_METHOD              0 (public_items)
                             30 PRECALL                  0
                             34 CALL                     0
                             44 GET_AWAITABLE            0
                             46 LOAD_CONST               0 (None)
                        >>   48 SEND                     3 (to 56)
                             50 YIELD_VALUE
                             52 RESUME                   3
                             54 JUMP_BACKWARD_NO_INTERRUPT     4 (to 48)
-                       >>   56 STORE_FAST               2 (data)
+                       >>   56 GET_ITER
+                       >>   58 FOR_ITER                28 (to 116)
+                            60 STORE_FAST               2 (item)
+               
+                41          62 LOAD_FAST                1 (object_id)
+                            64 LOAD_GLOBAL              3 (NULL + json)
+                            76 LOAD_ATTR                2 (dumps)
+                            86 LOAD_FAST                2 (item)
+                            88 PRECALL                  1
+                            92 CALL                     1
+                           102 CONTAINS_OP              0
+                           104 POP_JUMP_FORWARD_IF_FALSE     4 (to 114)
+               
+                42         106 LOAD_FAST                2 (item)
+                           108 SWAP                     2
+                           110 POP_TOP
+                           112 RETURN_VALUE
                
-                42          58 LOAD_GLOBAL              2 (logger)
-                            70 LOAD_METHOD              2 (debug)
-                            92 LOAD_GLOBAL              7 (NULL + json)
-                           104 LOAD_ATTR                4 (dumps)
-                           114 LOAD_FAST                2 (data)
-                           116 LOAD_CONST               1 (2)
-                           118 KW_NAMES                 2
-                           120 PRECALL                  2
-                           124 CALL                     2
-                           134 PRECALL                  1
-                           138 CALL                     1
-                           148 POP_TOP
-               
-                43         150 LOAD_FAST                2 (data)
-                           152 LOAD_METHOD              5 (get)
-                           174 LOAD_CONST               3 ('created_at')
-                           176 PRECALL                  1
-                           180 CALL                     1
-                           190 STORE_FAST               3 (created_at)
-               
-                44         192 LOAD_FAST                3 (created_at)
-                           194 POP_JUMP_FORWARD_IF_TRUE     2 (to 200)
-               
-                45         196 LOAD_CONST               0 (None)
-                           198 RETURN_VALUE
-               
-                46     >>  200 LOAD_GLOBAL             13 (NULL + datetime)
-                           212 LOAD_ATTR                7 (fromisoformat)
-                           222 LOAD_FAST                3 (created_at)
-                           224 LOAD_METHOD              8 (removesuffix)
-                           246 LOAD_CONST               4 ('Z')
-                           248 PRECALL                  1
-                           252 CALL                     1
-                           262 PRECALL                  1
-                           266 CALL                     1
-                           276 STORE_FAST               3 (created_at)
-               
-                47         278 LOAD_FAST                3 (created_at)
-                           280 LOAD_FAST                1 (published)
-                           282 COMPARE_OP               2 (==)
-                           288 POP_JUMP_FORWARD_IF_FALSE     2 (to 294)
+                41     >>  114 JUMP_BACKWARD           29 (to 58)
                
-                48         290 LOAD_FAST                2 (data)
-                           292 RETURN_VALUE
-               
-                49     >>  294 LOAD_CONST               0 (None)
-                           296 RETURN_VALUE
+                44     >>  116 LOAD_CONST               0 (None)
+                           118 RETURN_VALUE
                consts
                   None
-                  2
-                  ('indent',)
-                  'created_at'
-                  'Z'
-               names      ('top_public', 'logger', 'debug', 'json', 'dumps', 'get', 'datetime', 'fromisoformat', 'removesuffix')
-               varnames   ('self', 'published', 'data', 'created_at')
+               names      ('public_items', 'json', 'dumps')
+               varnames   ('self', 'object_id', 'item')
                freevars   ()
                cellvars   ()
                filename   '/woodpecker/src/codeberg.org/funfedidev/python_fediverse_pasture/fediverse_pasture/runner/application/mastodon.py'
-               name       'top_public_with_published'
-               firstlineno 40
-               lnotab 0x060134015c012a01040104014e010c010401
+               name       'top_public_with_object_id'
+               firstlineno 39
+               lnotab 0x060138012c0108ff0203
             'mastodon'
             'session'
             'application_name'
             code
                argcount  : 3
                nlocals   : 3
                stacksize : 5
                flags     : 3
                code
                   0x97007401000000000000000000007c017c006a010000000000000000a6
                   020000ab0200000000000000007c005f0200000000000000007407000000
                   000000000000007c00a00400000000000000000000000000000000000000
                   00a6000000ab0000000000000000007c006a0500000000000000007c02ac
                   01a6030000ab0300000000000000005300
-                51           0 RESUME                   0
+                46           0 RESUME                   0
                
-                54           2 LOAD_GLOBAL              1 (NULL + BearerAuthClient)
+                49           2 LOAD_GLOBAL              1 (NULL + BearerAuthClient)
                             14 LOAD_FAST                1 (session)
                             16 LOAD_FAST                0 (self)
                             18 LOAD_ATTR                1 (access_token)
                             28 PRECALL                  2
                             32 CALL                     2
                             42 LOAD_FAST                0 (self)
                             44 STORE_ATTR               2 (client)
                
-                56          54 LOAD_GLOBAL              7 (NULL + ApplicationAdapterForLastActivity)
+                51          54 LOAD_GLOBAL              7 (NULL + ApplicationAdapterForLastActivity)
                
-                57          66 LOAD_FAST                0 (self)
+                52          66 LOAD_FAST                0 (self)
                             68 LOAD_METHOD              4 (determine_actor_uri)
                             90 PRECALL                  0
                             94 CALL                     0
                
-                58         104 LOAD_FAST                0 (self)
-                           106 LOAD_ATTR                5 (top_public_with_published)
+                53         104 LOAD_FAST                0 (self)
+                           106 LOAD_ATTR                5 (top_public_with_object_id)
                
-                59         116 LOAD_FAST                2 (application_name)
+                54         116 LOAD_FAST                2 (application_name)
                
-                56         118 KW_NAMES                 1
+                51         118 KW_NAMES                 1
                            120 PRECALL                  3
                            124 CALL                     3
                            134 RETURN_VALUE
                consts
                   None
                   ('actor_uri', 'fetch_activity', 'application_name')
-               names      ('BearerAuthClient', 'access_token', 'client', 'ApplicationAdapterForLastActivity', 'determine_actor_uri', 'top_public_with_published')
+               names      ('BearerAuthClient', 'access_token', 'client', 'ApplicationAdapterForLastActivity', 'determine_actor_uri', 'top_public_with_object_id')
                varnames   ('self', 'session', 'application_name')
                freevars   ()
                cellvars   ()
                filename   '/woodpecker/src/codeberg.org/funfedidev/python_fediverse_pasture/fediverse_pasture/runner/application/mastodon.py'
                name       'last_activity'
-               firstlineno 51
+               firstlineno 46
                lnotab 0x020334020c0126010c0102fd
             ('mastodon',)
-         names      ('__name__', '__module__', '__qualname__', 'str', '__annotations__', 'client', 'BearerAuthClient', 'actor_uri', 'determine_actor_uri', 'top_public', 'datetime', 'dict', 'top_public_with_published', 'aiohttp', 'ClientSession', 'ApplicationAdapterForLastActivity', 'last_activity')
+         names      ('__name__', '__module__', '__qualname__', 'str', '__annotations__', 'client', 'BearerAuthClient', 'actor_uri', 'determine_actor_uri', 'public_items', 'dict', 'top_public_with_object_id', 'aiohttp', 'ClientSession', 'ApplicationAdapterForLastActivity', 'last_activity')
          varnames   ()
          freevars   ()
          cellvars   ()
          filename   '/woodpecker/src/codeberg.org/funfedidev/python_fediverse_pasture/fediverse_pasture/runner/application/mastodon.py'
          name       'MastodonApplication'
-         firstlineno 18
+         firstlineno 17
          lnotab
-            0x0c020a010a010a011401140206050609160c02ff04010cff020102ff02
+            0x0c020a010a010a011401140206050609160802ff04010cff020102ff02
             0202fe
       'MastodonApplication'
-   names      ('dataclasses', 'dataclass', 'datetime', 'logging', 'json', 'aiohttp', 'bovine.clients.bearer', 'BearerAuthClient', 'fediverse_pasture.types', 'ApplicationAdapterForLastActivity', 'getLogger', '__name__', 'logger', 'MastodonApplication')
+   names      ('dataclasses', 'dataclass', 'logging', 'json', 'aiohttp', 'bovine.clients.bearer', 'BearerAuthClient', 'fediverse_pasture.types', 'ApplicationAdapterForLastActivity', 'getLogger', '__name__', 'logger', 'MastodonApplication')
    varnames   ()
    freevars   ()
    cellvars   ()
    filename   '/woodpecker/src/codeberg.org/funfedidev/python_fediverse_pasture/fediverse_pasture/runner/application/mastodon.py'
    name       '<module>'
    firstlineno 1
-   lnotab 0x00ff02050c010c010801080108020c020c022003020118ff0e01
+   lnotab 0x00ff02050c010801080108020c020c022003020118ff0e01
```

### Comparing `fediverse_pasture-0.2.8/fediverse_pasture/runner/application/__pycache__/test_application.cpython-311-pytest-8.1.1.pyc` & `fediverse_pasture-0.2.9/fediverse_pasture/runner/application/__pycache__/test_application.cpython-311-pytest-8.1.1.pyc`

 * *Files 0% similar despite different names*

#### Python bytecode

```diff
@@ -1,9 +1,9 @@
 magic:    0xa70d0d0a
-moddate:  0xf44def65 (Mon Mar 11 18:31:16 2024 UTC)
+moddate:  0xa6340966 (Sun Mar 31 10:02:14 2024 UTC)
 files sz: 749
 code
    argcount  : 0
    nlocals   : 0
    stacksize : 3
    flags     : 0
    code
```

### Comparing `fediverse_pasture-0.2.8/fediverse_pasture/runner/application/bovine.py` & `fediverse_pasture-0.2.9/fediverse_pasture/runner/application/bovine.py`

 * *Files identical despite different names*

### Comparing `fediverse_pasture-0.2.8/fediverse_pasture/runner/application/firefish.py` & `fediverse_pasture-0.2.9/fediverse_pasture/runner/application/firefish.py`

 * *Files identical despite different names*

### Comparing `fediverse_pasture-0.2.8/fediverse_pasture/runner/application/mastodon.py` & `fediverse_pasture-0.2.9/fediverse_pasture/runner/application/mastodon.py`

 * *Files 16% similar despite different names*

```diff
@@ -1,13 +1,12 @@
-# SPDX-FileCopyrightText: 2023 Helge
+# SPDX-FileCopyrightText: 2023-2024 Helge
 #
 # SPDX-License-Identifier: MIT
 
 from dataclasses import dataclass
-from datetime import datetime
 import logging
 import json
 import aiohttp
 
 from bovine.clients.bearer import BearerAuthClient
 
 from fediverse_pasture.types import ApplicationAdapterForLastActivity
@@ -24,37 +23,33 @@
     actor_uri: str | None = None
 
     def determine_actor_uri(self):
         if self.actor_uri:
             return self.actor_uri
         return f"http://{self.domain}/users/{self.username}"
 
-    async def top_public(self):
+    async def public_items(self):
         response = await self.client.get(
             f"http://{self.domain}/api/v1/timelines/public"
         )
         public_timeline = await response.json()
         logger.debug(json.dumps(public_timeline, indent=2))
 
-        return public_timeline[0]
+        return public_timeline
+
+    async def top_public_with_object_id(self, object_id: str) -> dict | None:
+        for item in await self.public_items():
+            if object_id in json.dumps(item):
+                return item
 
-    async def top_public_with_published(self, published: datetime) -> dict | None:
-        data = await self.top_public()
-        logger.debug(json.dumps(data, indent=2))
-        created_at = data.get("created_at")
-        if not created_at:
-            return None
-        created_at = datetime.fromisoformat(created_at.removesuffix("Z"))
-        if created_at == published:
-            return data
         return None
 
     def last_activity(
         self, session: aiohttp.ClientSession, application_name: str = "mastodon"
     ) -> ApplicationAdapterForLastActivity:
         self.client = BearerAuthClient(session, self.access_token)
 
         return ApplicationAdapterForLastActivity(
             actor_uri=self.determine_actor_uri(),
-            fetch_activity=self.top_public_with_published,
+            fetch_activity=self.top_public_with_object_id,
             application_name=application_name,
         )
```

### Comparing `fediverse_pasture-0.2.8/fediverse_pasture/runner/application/test_application.py` & `fediverse_pasture-0.2.9/fediverse_pasture/runner/application/test_application.py`

 * *Files identical despite different names*

### Comparing `fediverse_pasture-0.2.8/fediverse_pasture/runner/entry.py` & `fediverse_pasture-0.2.9/fediverse_pasture/runner/entry.py`

 * *Files identical despite different names*

### Comparing `fediverse_pasture-0.2.8/fediverse_pasture/runner/result_store.py` & `fediverse_pasture-0.2.9/fediverse_pasture/runner/result_store.py`

 * *Files identical despite different names*

### Comparing `fediverse_pasture-0.2.8/fediverse_pasture/runner/test_activity_sender.py` & `fediverse_pasture-0.2.9/fediverse_pasture/runner/test_activity_sender.py`

 * *Files identical despite different names*

### Comparing `fediverse_pasture-0.2.8/fediverse_pasture/runner/test_entry.py` & `fediverse_pasture-0.2.9/fediverse_pasture/runner/test_entry.py`

 * *Files identical despite different names*

### Comparing `fediverse_pasture-0.2.8/fediverse_pasture/runner/test_result_store.py` & `fediverse_pasture-0.2.9/fediverse_pasture/runner/test_result_store.py`

 * *Files identical despite different names*

### Comparing `fediverse_pasture-0.2.8/fediverse_pasture/runner/test_verify_actor.py` & `fediverse_pasture-0.2.9/fediverse_pasture/runner/test_verify_actor.py`

 * *Files identical despite different names*

### Comparing `fediverse_pasture-0.2.8/fediverse_pasture/runner/verify_actor.py` & `fediverse_pasture-0.2.9/fediverse_pasture/runner/verify_actor.py`

 * *Files identical despite different names*

### Comparing `fediverse_pasture-0.2.8/fediverse_pasture/server/__init__.py` & `fediverse_pasture-0.2.9/fediverse_pasture/server/__init__.py`

 * *Files identical despite different names*

### Comparing `fediverse_pasture-0.2.8/fediverse_pasture/server/__pycache__/__init__.cpython-311.pyc` & `fediverse_pasture-0.2.9/fediverse_pasture/server/__pycache__/__init__.cpython-311.pyc`

 * *Files 0% similar despite different names*

#### Python bytecode

```diff
@@ -1,9 +1,9 @@
 magic:    0xa70d0d0a
-moddate:  0xf44def65 (Mon Mar 11 18:31:16 2024 UTC)
+moddate:  0xa6340966 (Sun Mar 31 10:02:14 2024 UTC)
 files sz: 6266
 code
    argcount  : 0
    nlocals   : 0
    stacksize : 5
    flags     : 0
    code
```

### Comparing `fediverse_pasture-0.2.8/fediverse_pasture/server/__pycache__/http_signature.cpython-311.pyc` & `fediverse_pasture-0.2.9/fediverse_pasture/server/__pycache__/http_signature.cpython-311.pyc`

 * *Files 1% similar despite different names*

#### Python bytecode

```diff
@@ -1,9 +1,9 @@
 magic:    0xa70d0d0a
-moddate:  0xf44def65 (Mon Mar 11 18:31:16 2024 UTC)
+moddate:  0xa6340966 (Sun Mar 31 10:02:14 2024 UTC)
 files sz: 2203
 code
    argcount  : 0
    nlocals   : 0
    stacksize : 4
    flags     : 0
    code
```

### Comparing `fediverse_pasture-0.2.8/fediverse_pasture/server/__pycache__/image_provider_blueprint.cpython-311.pyc` & `fediverse_pasture-0.2.9/fediverse_pasture/server/__pycache__/image_provider_blueprint.cpython-311.pyc`

 * *Files 1% similar despite different names*

#### Python bytecode

```diff
@@ -1,9 +1,9 @@
 magic:    0xa70d0d0a
-moddate:  0xf44def65 (Mon Mar 11 18:31:16 2024 UTC)
+moddate:  0xa6340966 (Sun Mar 31 10:02:14 2024 UTC)
 files sz: 1245
 code
    argcount  : 0
    nlocals   : 0
    stacksize : 4
    flags     : 0
    code
```

### Comparing `fediverse_pasture-0.2.8/fediverse_pasture/server/__pycache__/parser.cpython-311.pyc` & `fediverse_pasture-0.2.9/fediverse_pasture/server/__pycache__/parser.cpython-311.pyc`

 * *Files 8% similar despite different names*

#### Python bytecode

```diff
@@ -1,9 +1,9 @@
 magic:    0xa70d0d0a
-moddate:  0xf44def65 (Mon Mar 11 18:31:16 2024 UTC)
+moddate:  0xa6340966 (Sun Mar 31 10:02:14 2024 UTC)
 files sz: 346
 code
    argcount  : 0
    nlocals   : 0
    stacksize : 4
    flags     : 0
    code
```

### Comparing `fediverse_pasture-0.2.8/fediverse_pasture/server/__pycache__/test_actor_public_key.cpython-311-pytest-8.1.1.pyc` & `fediverse_pasture-0.2.9/fediverse_pasture/server/__pycache__/test_actor_public_key.cpython-311-pytest-8.1.1.pyc`

 * *Files 0% similar despite different names*

#### Python bytecode

```diff
@@ -1,9 +1,9 @@
 magic:    0xa70d0d0a
-moddate:  0xf44def65 (Mon Mar 11 18:31:16 2024 UTC)
+moddate:  0xa6340966 (Sun Mar 31 10:02:14 2024 UTC)
 files sz: 3328
 code
    argcount  : 0
    nlocals   : 0
    stacksize : 6
    flags     : 0
    code
```

### Comparing `fediverse_pasture-0.2.8/fediverse_pasture/server/__pycache__/test_assets_blueprint.cpython-311-pytest-8.1.1.pyc` & `fediverse_pasture-0.2.9/fediverse_pasture/server/__pycache__/test_assets_blueprint.cpython-311-pytest-8.1.1.pyc`

 * *Files 2% similar despite different names*

#### Python bytecode

```diff
@@ -1,9 +1,9 @@
 magic:    0xa70d0d0a
-moddate:  0xf44def65 (Mon Mar 11 18:31:16 2024 UTC)
+moddate:  0xa6340966 (Sun Mar 31 10:02:14 2024 UTC)
 files sz: 879
 code
    argcount  : 0
    nlocals   : 0
    stacksize : 2
    flags     : 0
    code
```

### Comparing `fediverse_pasture-0.2.8/fediverse_pasture/server/__pycache__/test_blueprint.cpython-311-pytest-8.1.1.pyc` & `fediverse_pasture-0.2.9/fediverse_pasture/server/__pycache__/test_blueprint.cpython-311-pytest-8.1.1.pyc`

 * *Files 1% similar despite different names*

#### Python bytecode

```diff
@@ -1,9 +1,9 @@
 magic:    0xa70d0d0a
-moddate:  0xf44def65 (Mon Mar 11 18:31:16 2024 UTC)
+moddate:  0xa6340966 (Sun Mar 31 10:02:14 2024 UTC)
 files sz: 1167
 code
    argcount  : 0
    nlocals   : 0
    stacksize : 2
    flags     : 0
    code
```

### Comparing `fediverse_pasture-0.2.8/fediverse_pasture/server/__pycache__/test_blueprint_http_check.cpython-311-pytest-8.1.1.pyc` & `fediverse_pasture-0.2.9/fediverse_pasture/server/__pycache__/test_blueprint_http_check.cpython-311-pytest-8.1.1.pyc`

 * *Files 1% similar despite different names*

#### Python bytecode

```diff
@@ -1,9 +1,9 @@
 magic:    0xa70d0d0a
-moddate:  0xf44def65 (Mon Mar 11 18:31:16 2024 UTC)
+moddate:  0xa6340966 (Sun Mar 31 10:02:14 2024 UTC)
 files sz: 877
 code
    argcount  : 0
    nlocals   : 0
    stacksize : 2
    flags     : 0
    code
```

### Comparing `fediverse_pasture-0.2.8/fediverse_pasture/server/__pycache__/test_http_signature.cpython-311-pytest-8.1.1.pyc` & `fediverse_pasture-0.2.9/fediverse_pasture/server/__pycache__/test_http_signature.cpython-311-pytest-8.1.1.pyc`

 * *Files 2% similar despite different names*

#### Python bytecode

```diff
@@ -1,9 +1,9 @@
 magic:    0xa70d0d0a
-moddate:  0xf44def65 (Mon Mar 11 18:31:16 2024 UTC)
+moddate:  0xa6340966 (Sun Mar 31 10:02:14 2024 UTC)
 files sz: 830
 code
    argcount  : 0
    nlocals   : 0
    stacksize : 2
    flags     : 0
    code
```

### Comparing `fediverse_pasture-0.2.8/fediverse_pasture/server/__pycache__/test_image_provider_blueprint.cpython-311-pytest-8.1.1.pyc` & `fediverse_pasture-0.2.9/fediverse_pasture/server/__pycache__/test_image_provider_blueprint.cpython-311-pytest-8.1.1.pyc`

 * *Files 6% similar despite different names*

#### Python bytecode

```diff
@@ -1,9 +1,9 @@
 magic:    0xa70d0d0a
-moddate:  0xf44def65 (Mon Mar 11 18:31:16 2024 UTC)
+moddate:  0xa6340966 (Sun Mar 31 10:02:14 2024 UTC)
 files sz: 482
 code
    argcount  : 0
    nlocals   : 0
    stacksize : 2
    flags     : 0
    code
```

### Comparing `fediverse_pasture-0.2.8/fediverse_pasture/server/__pycache__/test_parser.cpython-311-pytest-8.1.1.pyc` & `fediverse_pasture-0.2.9/fediverse_pasture/server/__pycache__/test_parser.cpython-311-pytest-8.1.1.pyc`

 * *Files 1% similar despite different names*

#### Python bytecode

```diff
@@ -1,9 +1,9 @@
 magic:    0xa70d0d0a
-moddate:  0xf44def65 (Mon Mar 11 18:31:16 2024 UTC)
+moddate:  0xa6340966 (Sun Mar 31 10:02:14 2024 UTC)
 files sz: 626
 code
    argcount  : 0
    nlocals   : 0
    stacksize : 8
    flags     : 0
    code
```

### Comparing `fediverse_pasture-0.2.8/fediverse_pasture/server/__pycache__/test_verify_actor.cpython-311-pytest-8.1.1.pyc` & `fediverse_pasture-0.2.9/fediverse_pasture/server/__pycache__/test_verify_actor.cpython-311-pytest-8.1.1.pyc`

 * *Files 1% similar despite different names*

#### Python bytecode

```diff
@@ -1,9 +1,9 @@
 magic:    0xa70d0d0a
-moddate:  0xf44def65 (Mon Mar 11 18:31:16 2024 UTC)
+moddate:  0xa6340966 (Sun Mar 31 10:02:14 2024 UTC)
 files sz: 1385
 code
    argcount  : 0
    nlocals   : 0
    stacksize : 5
    flags     : 0
    code
```

### Comparing `fediverse_pasture-0.2.8/fediverse_pasture/server/__pycache__/utils.cpython-311.pyc` & `fediverse_pasture-0.2.9/fediverse_pasture/server/__pycache__/utils.cpython-311.pyc`

 * *Files 0% similar despite different names*

#### Python bytecode

```diff
@@ -1,9 +1,9 @@
 magic:    0xa70d0d0a
-moddate:  0xf44def65 (Mon Mar 11 18:31:16 2024 UTC)
+moddate:  0xa6340966 (Sun Mar 31 10:02:14 2024 UTC)
 files sz: 6930
 code
    argcount  : 0
    nlocals   : 0
    stacksize : 9
    flags     : 0
    code
```

### Comparing `fediverse_pasture-0.2.8/fediverse_pasture/server/__pycache__/verify_actor.cpython-311.pyc` & `fediverse_pasture-0.2.9/fediverse_pasture/server/__pycache__/verify_actor.cpython-311.pyc`

 * *Files 0% similar despite different names*

#### Python bytecode

```diff
@@ -1,9 +1,9 @@
 magic:    0xa70d0d0a
-moddate:  0xf44def65 (Mon Mar 11 18:31:16 2024 UTC)
+moddate:  0xa6340966 (Sun Mar 31 10:02:14 2024 UTC)
 files sz: 10051
 code
    argcount  : 0
    nlocals   : 0
    stacksize : 5
    flags     : 0
    code
```

### Comparing `fediverse_pasture-0.2.8/fediverse_pasture/server/http_signature.py` & `fediverse_pasture-0.2.9/fediverse_pasture/server/http_signature.py`

 * *Files identical despite different names*

### Comparing `fediverse_pasture-0.2.8/fediverse_pasture/server/image_provider_blueprint.py` & `fediverse_pasture-0.2.9/fediverse_pasture/server/image_provider_blueprint.py`

 * *Files identical despite different names*

### Comparing `fediverse_pasture-0.2.8/fediverse_pasture/server/test_actor_public_key.py` & `fediverse_pasture-0.2.9/fediverse_pasture/server/test_actor_public_key.py`

 * *Files identical despite different names*

### Comparing `fediverse_pasture-0.2.8/fediverse_pasture/server/test_assets_blueprint.py` & `fediverse_pasture-0.2.9/fediverse_pasture/server/test_assets_blueprint.py`

 * *Files identical despite different names*

### Comparing `fediverse_pasture-0.2.8/fediverse_pasture/server/test_blueprint.py` & `fediverse_pasture-0.2.9/fediverse_pasture/server/test_blueprint.py`

 * *Files identical despite different names*

### Comparing `fediverse_pasture-0.2.8/fediverse_pasture/server/test_blueprint_http_check.py` & `fediverse_pasture-0.2.9/fediverse_pasture/server/test_blueprint_http_check.py`

 * *Files identical despite different names*

### Comparing `fediverse_pasture-0.2.8/fediverse_pasture/server/test_http_signature.py` & `fediverse_pasture-0.2.9/fediverse_pasture/server/test_http_signature.py`

 * *Files identical despite different names*

### Comparing `fediverse_pasture-0.2.8/fediverse_pasture/server/test_parser.py` & `fediverse_pasture-0.2.9/fediverse_pasture/server/test_parser.py`

 * *Files identical despite different names*

### Comparing `fediverse_pasture-0.2.8/fediverse_pasture/server/test_verify_actor.py` & `fediverse_pasture-0.2.9/fediverse_pasture/server/test_verify_actor.py`

 * *Files identical despite different names*

### Comparing `fediverse_pasture-0.2.8/fediverse_pasture/server/utils.py` & `fediverse_pasture-0.2.9/fediverse_pasture/server/utils.py`

 * *Files identical despite different names*

### Comparing `fediverse_pasture-0.2.8/fediverse_pasture/server/verify_actor.py` & `fediverse_pasture-0.2.9/fediverse_pasture/server/verify_actor.py`

 * *Files identical despite different names*

### Comparing `fediverse_pasture-0.2.8/fediverse_pasture/templates/FediverseLogo.svg` & `fediverse_pasture-0.2.9/fediverse_pasture/templates/FediverseLogo.svg`

 * *Files identical despite different names*

### Comparing `fediverse_pasture-0.2.8/fediverse_pasture/templates/index.html.j2` & `fediverse_pasture-0.2.9/fediverse_pasture/templates/index.html.j2`

 * *Files identical despite different names*

### Comparing `fediverse_pasture-0.2.8/fediverse_pasture/templates/styles.css` & `fediverse_pasture-0.2.9/fediverse_pasture/templates/styles.css`

 * *Files identical despite different names*

### Comparing `fediverse_pasture-0.2.8/fediverse_pasture/templates/verify_actor_result.html.j2` & `fediverse_pasture-0.2.9/fediverse_pasture/templates/verify_actor_result.html.j2`

 * *Files identical despite different names*

### Comparing `fediverse_pasture-0.2.8/fediverse_pasture/types.py` & `fediverse_pasture-0.2.9/fediverse_pasture/types.py`

 * *Files identical despite different names*

### Comparing `fediverse_pasture-0.2.8/fediverse_pasture/verify_actor.py` & `fediverse_pasture-0.2.9/fediverse_pasture/verify_actor.py`

 * *Files identical despite different names*

### Comparing `fediverse_pasture-0.2.8/pyproject.toml` & `fediverse_pasture-0.2.9/pyproject.toml`

 * *Files 0% similar despite different names*

```diff
@@ -1,14 +1,14 @@
 # SPDX-FileCopyrightText: 2023 Helge
 #
 # SPDX-License-Identifier: MIT
 
 [tool.poetry]
 name = "fediverse-pasture"
-version = "0.2.8"
+version = "0.2.9"
 description = "Helpful tools to test Fediverse Applications"
 authors = ["Helge <helge.krueger@gmail.com>"]
 readme = "README.md"
 packages = [{include = "fediverse_pasture"}]
 repository = "https://codeberg.org/funfedidev/python_fediverse_pasture"
 documentation = "https://funfedi.dev/python_package/"
 license = "MIT"
```

### Comparing `fediverse_pasture-0.2.8/PKG-INFO` & `fediverse_pasture-0.2.9/PKG-INFO`

 * *Files 0% similar despite different names*

```diff
@@ -1,10 +1,10 @@
 Metadata-Version: 2.1
 Name: fediverse-pasture
-Version: 0.2.8
+Version: 0.2.9
 Summary: Helpful tools to test Fediverse Applications
 Home-page: https://codeberg.org/funfedidev/python_fediverse_pasture
 License: MIT
 Author: Helge
 Author-email: helge.krueger@gmail.com
 Requires-Python: >=3.11,<4.0
 Classifier: License :: OSI Approved :: MIT License
```

